{
  "generated_at_iso": "2026-04-21T16:10:02.078981+00:00",
  "tokens": [
    {
      "symbol": "LFP",
      "chain": "solana",
      "token_address": "8jPSBB5Ebp6bRWJzwstUEm4Xs2p2jQadewyyxedxbrrr",
      "score": 14.67,
      "fdv": 105752,
      "volume_h24": 50838.59,
      "price_change_h1": 48.41,
      "price_change_h6": 31.73,
      "avg_buy_usd": 0,
      "total_buy_usd": 0,
      "buyer_count": 0,
      "buyer_wallets": [],
      "top_buyer_score": 0,
      "gmgn_smart_wallets": 0,
      "mcap_tier": "$50K-$250K",
      "dex_url": "https://dexscreener.com/solana/5aj8ktuw27g61qypmhyeqp6nh7wqywvuzsdpmmanhkzz",
      "positives": [
        "burned"
      ],
      "age_hours": 1.586398424275716
    },
    {
      "symbol": "Curak",
      "chain": "solana",
      "token_address": "EEmHzKKTcuG4XS178MuYjbp4DPF7s3xZcsGoJfCpump",
      "score": 10.12,
      "fdv": 73799,
      "volume_h24": 191844.98,
      "price_change_h1": 109,
      "price_change_h6": 109,
      "avg_buy_usd": 0,
      "total_buy_usd": 0,
      "buyer_count": 0,
      "buyer_wallets": [],
      "top_buyer_score": 0,
      "gmgn_smart_wallets": 0,
      "mcap_tier": "$50K-$250K",
      "dex_url": "https://dexscreener.com/solana/jdb4wsxbkdtcskrkeh7nbsmorhtxkbccthdqfa48nlb1",
      "positives": [
        "burned"
      ],
      "age_hours": 0.6557382784016927
    },
    {
      "symbol": "TERMINAL",
      "chain": "solana",
      "token_address": "NjixGUrygRPWquTCgVzy2czJKzZ5pLCthafS675pump",
      "score": 10.12,
      "fdv": 76572,
      "volume_h24": 446889.89,
      "price_change_h1": 121,
      "price_change_h6": 121,
      "avg_buy_usd": 0,
      "total_buy_usd": 0,
      "buyer_count": 0,
      "buyer_wallets": [],
      "top_buyer_score": 0,
      "gmgn_smart_wallets": 0,
      "mcap_tier": "$50K-$250K",
      "dex_url": "https://dexscreener.com/solana/9w3azedencxrbrrc6utrcgqdjasmtvjrfk8ulemt9zh9",
      "positives": [
        "burned"
      ],
      "age_hours": 0.49769562201605905
    },
    {
      "symbol": "PVE",
      "chain": "solana",
      "token_address": "BGrHmunURNXBmiX7g2uwrPZWtYgQjbQFNPu4GCrhpump",
      "score": 9.36,
      "fdv": 59176,
      "volume_h24": 76604.46,
      "price_change_h1": 76.15,
      "price_change_h6": 76.15,
      "avg_buy_usd": 0,
      "total_buy_usd": 0,
      "buyer_count": 0,
      "buyer_wallets": [],
      "top_buyer_score": 0,
      "gmgn_smart_wallets": 0,
      "mcap_tier": "$50K-$250K",
      "dex_url": "https://dexscreener.com/solana/arrl9oafls8jg4gfq1dhbaxmqq7qiaomh8eqa1a9ibcr",
      "positives": [
        "burned"
      ],
      "age_hours": 0.5458880479600694
    },
    {
      "symbol": "8",
      "chain": "solana",
      "token_address": "3pJz4wjYfRnMc5pc9rYBgJwMiSsoHAwLtfECjNwbpump",
      "score": 7.59,
      "fdv": 29807,
      "volume_h24": 84610.03,
      "price_change_h1": -15.62,
      "price_change_h6": -15.62,
      "avg_buy_usd": 0,
      "total_buy_usd": 0,
      "buyer_count": 0,
      "buyer_wallets": [],
      "top_buyer_score": 0,
      "gmgn_smart_wallets": 0,
      "mcap_tier": "<$50K",
      "dex_url": "https://dexscreener.com/solana/7u8tpq6xe3ohgtyemazrsnp9juxttpmnku3jlenvxknn",
      "positives": [
        "burned"
      ],
      "age_hours": 0.9526956538221572
    },
    {
      "symbol": "wif2",
      "chain": "solana",
      "token_address": "9tCjcZFwaqMFSFkiYDRAGd3kxChxVguHDCREb6eSpump",
      "score": 5.06,
      "fdv": 300750,
      "volume_h24": 3230148.3,
      "price_change_h1": 13.6,
      "price_change_h6": -44.34,
      "avg_buy_usd": 0,
      "total_buy_usd": 0,
      "buyer_count": 0,
      "buyer_wallets": [],
      "top_buyer_score": 0,
      "gmgn_smart_wallets": 0,
      "mcap_tier": "$250K-$1M",
      "dex_url": "https://dexscreener.com/solana/89kpf7x5sqdm8ko4gvzzslzd7w57tg9jutcqokqxcimi",
      "positives": [
        "burned"
      ],
      "age_hours": 10.406539304402669
    },
    {
      "symbol": "APU",
      "chain": "solana",
      "token_address": "CKPmmwT3YRheAUrhL4oQENwcvxxt4HgZf1ptcDSWCjp4",
      "score": 4.25,
      "fdv": 351062,
      "volume_h24": 585492.62,
      "price_change_h1": 57.41,
      "price_change_h6": 665,
      "avg_buy_usd": 0,
      "total_buy_usd": 0,
      "buyer_count": 0,
      "buyer_wallets": [],
      "top_buyer_score": 0,
      "gmgn_smart_wallets": 0,
      "mcap_tier": "$250K-$1M",
      "dex_url": "https://dexscreener.com/solana/fen7hbwloarpdv15vm1kxzmzmfts4geax9mnwuf6vi1g",
      "positives": [
        "burned"
      ],
      "age_hours": 10.467372606608073
    },
    {
      "symbol": "brrp",
      "chain": "solana",
      "token_address": "DsTQ67tKPAs88Xo8oPYkZ1CEnPn2rGm9asus4Z3Zbrrr",
      "score": 4.05,
      "fdv": 47165,
      "volume_h24": 148766.83,
      "price_change_h1": 58.51,
      "price_change_h6": 525,
      "avg_buy_usd": 0,
      "total_buy_usd": 0,
      "buyer_count": 0,
      "buyer_wallets": [],
      "top_buyer_score": 0,
      "gmgn_smart_wallets": 0,
      "mcap_tier": "<$50K",
      "dex_url": "https://dexscreener.com/solana/78csycdckehfsoehvl4lyqsqpebeqiduusmenktzygp5",
      "positives": [
        "burned"
      ],
      "age_hours": 16.53075120388455
    },
    {
      "symbol": "ASTERWOJAK",
      "chain": "solana",
      "token_address": "7VyTxnWEbM6nkq3w9DMDN3xEcc2TEs4a3sBnKyCCpump",
      "score": 4.05,
      "fdv": 185634,
      "volume_h24": 681754.24,
      "price_change_h1": 24.94,
      "price_change_h6": 413,
      "avg_buy_usd": 0,
      "total_buy_usd": 0,
      "buyer_count": 0,
      "buyer_wallets": [],
      "top_buyer_score": 0,
      "gmgn_smart_wallets": 0,
      "mcap_tier": "$50K-$250K",
      "dex_url": "https://dexscreener.com/solana/dvjai9nq8m6tky522wwdxtzshckoyw9cobkumbxzp3me",
      "positives": [
        "burned"
      ],
      "age_hours": 1.6160289594184027
    },
    {
      "symbol": "WIF2",
      "chain": "solana",
      "token_address": "8poMrk6zvrMPJU2K8hZYitfBAXpXPt1PCrpyFJ27pump",
      "score": 2.02,
      "fdv": 81452,
      "volume_h24": 164721.23,
      "price_change_h1": 6.17,
      "price_change_h6": 135,
      "avg_buy_usd": 0,
      "total_buy_usd": 0,
      "buyer_count": 0,
      "buyer_wallets": [],
      "top_buyer_score": 0,
      "gmgn_smart_wallets": 0,
      "mcap_tier": "$50K-$250K",
      "dex_url": "https://dexscreener.com/solana/4olj9fnsvbf5cs9dhx9qesre5ieiwj5gdmynagxv1eva",
      "positives": [
        "burned"
      ],
      "age_hours": 3.373849986843533
    },
    {
      "symbol": "GME",
      "chain": "solana",
      "token_address": "4wMWXp7okGLbTcJpcmhfoVNa3B2JLx2yuzGFD51Ppump",
      "score": 1.77,
      "fdv": 78918,
      "volume_h24": 931640.63,
      "price_change_h1": -8.65,
      "price_change_h6": 51.75,
      "avg_buy_usd": 0,
      "total_buy_usd": 0,
      "buyer_count": 0,
      "buyer_wallets": [],
      "top_buyer_score": 0,
      "gmgn_smart_wallets": 0,
      "mcap_tier": "$50K-$250K",
      "dex_url": "https://dexscreener.com/solana/4xh46rub6zmspey24jvx1yne7wzwnsibtyupgzezfrfg",
      "positives": [
        "burned"
      ],
      "age_hours": 16.817973413628472
    },
    {
      "symbol": "SIF",
      "chain": "solana",
      "token_address": "554b7hiCBBbd1wT7XvqRMhsCcFuHSFXkfZdTeVzupump",
      "score": 0.94,
      "fdv": 40666,
      "volume_h24": 806854.85,
      "price_change_h1": -48.83,
      "price_change_h6": -27.03,
      "avg_buy_usd": 0,
      "total_buy_usd": 0,
      "buyer_count": 0,
      "buyer_wallets": [],
      "top_buyer_score": 0,
      "gmgn_smart_wallets": 0,
      "mcap_tier": "<$50K",
      "dex_url": "https://dexscreener.com/solana/8hflqa1stnk1ps9qtjfegllukeh3uyjrha5vku1q4pwg",
      "positives": [
        "burned"
      ],
      "age_hours": 7.482094813774957
    },
    {
      "symbol": "buzzed",
      "chain": "solana",
      "token_address": "6SFu8ZbQZxZYKf3rE7uxw1GLD97DQKbMM7VffgcWpump",
      "score": 0.89,
      "fdv": 103593,
      "volume_h24": 229056.59,
      "price_change_h1": -26.99,
      "price_change_h6": 23.43,
      "avg_buy_usd": 0,
      "total_buy_usd": 0,
      "buyer_count": 0,
      "buyer_wallets": [],
      "top_buyer_score": 0,
      "gmgn_smart_wallets": 0,
      "mcap_tier": "$50K-$250K",
      "dex_url": "https://dexscreener.com/solana/26onduwpyssmgske9igqlvf9rf2avchho8t19mhftyev",
      "positives": [
        "burned"
      ],
      "age_hours": 18.72226774509006
    },
    {
      "symbol": "PSYCHO",
      "chain": "solana",
      "token_address": "dA5zv9z3FnDGsWi5eeNsRDqFuzrcP4CXEzehy8Xpump",
      "score": 0.76,
      "fdv": 32600,
      "volume_h24": 249320.21,
      "price_change_h1": -22.92,
      "price_change_h6": -7.89,
      "avg_buy_usd": 0,
      "total_buy_usd": 0,
      "buyer_count": 0,
      "buyer_wallets": [],
      "top_buyer_score": 0,
      "gmgn_smart_wallets": 0,
      "mcap_tier": "<$50K",
      "dex_url": "https://dexscreener.com/solana/2m6qzx7pepehw8ca1hsoo1puxkmtwbbd9ae95wdxmngr",
      "positives": [
        "burned"
      ],
      "age_hours": 11.270323303697374
    },
    {
      "symbol": "MHGA",
      "chain": "solana",
      "token_address": "2b9iJWg3sppbAAQMuKBXa1iuSSsuPvKwcdiA4VdNpump",
      "score": 0.53,
      "fdv": 20154,
      "volume_h24": 381932.25,
      "price_change_h1": -9.93,
      "price_change_h6": -42.08,
      "avg_buy_usd": 0,
      "total_buy_usd": 0,
      "buyer_count": 0,
      "buyer_wallets": [],
      "top_buyer_score": 0,
      "gmgn_smart_wallets": 0,
      "mcap_tier": "<$50K",
      "dex_url": "https://dexscreener.com/solana/8okfo9vs25mgnjohz9hss2b5ps4oenfymdsc5unfknte",
      "positives": [
        "burned"
      ],
      "age_hours": 3.411261487223307
    },
    {
      "symbol": "ASTEROID",
      "chain": "solana",
      "token_address": "8cyRcHC2iiupSCMR8uf5TPnLGr3j4Dwe3EJ2A4fUpump",
      "score": 0.5,
      "fdv": 15184,
      "volume_h24": 287898.15,
      "price_change_h1": -15.03,
      "price_change_h6": 19.37,
      "avg_buy_usd": 0,
      "total_buy_usd": 0,
      "buyer_count": 0,
      "buyer_wallets": [],
      "top_buyer_score": 0,
      "gmgn_smart_wallets": 0,
      "mcap_tier": "<$50K",
      "dex_url": "https://dexscreener.com/solana/dypffqjnwxf7yra3trjtsabaacafnzreltgnadqwfwyv",
      "positives": [
        "burned"
      ],
      "age_hours": 13.920323297458225
    },
    {
      "symbol": "Outsider",
      "chain": "solana",
      "token_address": "7Zc39KqgscQVqtjPkeB3fecEzVd9gYHAptPSLiC9pump",
      "score": 0.5,
      "fdv": 22203,
      "volume_h24": 407790.75,
      "price_change_h1": 35.87,
      "price_change_h6": -37.12,
      "avg_buy_usd": 0,
      "total_buy_usd": 0,
      "buyer_count": 0,
      "buyer_wallets": [],
      "top_buyer_score": 0,
      "gmgn_smart_wallets": 0,
      "mcap_tier": "<$50K",
      "dex_url": "https://dexscreener.com/solana/gujxksrdgwktz2stumsvbnjsvxczw3bkovglpwzkuabn",
      "positives": [
        "burned"
      ],
      "age_hours": 4.255565087483724
    },
    {
      "symbol": "Bitshark",
      "chain": "solana",
      "token_address": "GaJxMSdqEJ7suiKqF7kSjR5kQjqP4ukaracp2bELpump",
      "score": 0.46,
      "fdv": 26569,
      "volume_h24": 353938.91,
      "price_change_h1": -9.35,
      "price_change_h6": -39.54,
      "avg_buy_usd": 0,
      "total_buy_usd": 0,
      "buyer_count": 0,
      "buyer_wallets": [],
      "top_buyer_score": 0,
      "gmgn_smart_wallets": 0,
      "mcap_tier": "<$50K",
      "dex_url": "https://dexscreener.com/solana/ekmqwx6pz4kycav87sk4szcyxk6w9hyrfw9ftegwvu3t",
      "positives": [
        "burned"
      ],
      "age_hours": 6.093620640530056
    },
    {
      "symbol": "trust",
      "chain": "solana",
      "token_address": "3zxyYUZ5qF6tY5Sg2Wc9vqPucyZUX5m917pTgZSfpump",
      "score": 0.4,
      "fdv": 17136,
      "volume_h24": 836776.4,
      "price_change_h1": -5.25,
      "price_change_h6": -38.79,
      "avg_buy_usd": 0,
      "total_buy_usd": 0,
      "buyer_count": 0,
      "buyer_wallets": [],
      "top_buyer_score": 0,
      "gmgn_smart_wallets": 0,
      "mcap_tier": "<$50K",
      "dex_url": "https://dexscreener.com/solana/4skx3rayfeuctadcfccagvw3cnvrtswzc21regvfmkvb",
      "positives": [
        "burned"
      ],
      "age_hours": 20.230983751695423
    },
    {
      "symbol": "MOG",
      "chain": "solana",
      "token_address": "71Ys7KutNBqoPtAkhdSALCpBZArnXaywYsxfM58tpump",
      "score": 0.18,
      "fdv": 31500,
      "volume_h24": 256118.78,
      "price_change_h1": -16.26,
      "price_change_h6": -70.06,
      "avg_buy_usd": 0,
      "total_buy_usd": 0,
      "buyer_count": 0,
      "buyer_wallets": [],
      "top_buyer_score": 0,
      "gmgn_smart_wallets": 0,
      "mcap_tier": "<$50K",
      "dex_url": "https://dexscreener.com/solana/fcd5srvp7z4ehuwga4vyughmtugwbeli7ynmnpy1vb7y",
      "positives": [
        "burned"
      ],
      "age_hours": 12.210150380520291
    },
    {
      "symbol": "FINCEPT",
      "chain": "solana",
      "token_address": "J7Xrcq6cX4GZ3mnQXvrsCYGQyijc9gSNZT4DSUijpump",
      "score": 0.1,
      "fdv": 15385,
      "volume_h24": 145852.15,
      "price_change_h1": 8.88,
      "price_change_h6": -50.98,
      "avg_buy_usd": 0,
      "total_buy_usd": 0,
      "buyer_count": 0,
      "buyer_wallets": [],
      "top_buyer_score": 0,
      "gmgn_smart_wallets": 0,
      "mcap_tier": "<$50K",
      "dex_url": "https://dexscreener.com/solana/dz15qjxuio9a9mwvfh6bcldzkmahntaa4zrc7mscqvmd",
      "positives": [
        "burned"
      ],
      "age_hours": 6.770009531114367
    },
    {
      "symbol": "BRR",
      "chain": "solana",
      "token_address": "BVurm1fJBbveXQRSYfSnjAfSeZqVKcmgbRYReFyXbrrr",
      "score": 0.09,
      "fdv": 11479,
      "volume_h24": 143611.8,
      "price_change_h1": -47.55,
      "price_change_h6": -68.15,
      "avg_buy_usd": 0,
      "total_buy_usd": 0,
      "buyer_count": 0,
      "buyer_wallets": [],
      "top_buyer_score": 0,
      "gmgn_smart_wallets": 0,
      "mcap_tier": "<$50K",
      "dex_url": "https://dexscreener.com/solana/daugjqvadk4hn4yatyiwmaaschb1wwke4rn4qkgadd7g",
      "positives": [
        "burned"
      ],
      "age_hours": 2.8815845335557726
    },
    {
      "symbol": "PNZI",
      "chain": "solana",
      "token_address": "9hXCPbWZQ4pxFxgh55Ejz1iLZ6g6E1cT61u8urUvpump",
      "score": 0.09,
      "fdv": 10277,
      "volume_h24": 136537.7,
      "price_change_h1": -10.23,
      "price_change_h6": -69.51,
      "avg_buy_usd": 0,
      "total_buy_usd": 0,
      "buyer_count": 0,
      "buyer_wallets": [],
      "top_buyer_score": 0,
      "gmgn_smart_wallets": 0,
      "mcap_tier": "<$50K",
      "dex_url": "https://dexscreener.com/solana/ggf8uabdbyw4dxpachra1ftxelvowdftxmkgrmhgsznp",
      "positives": [
        "burned"
      ],
      "age_hours": 5.618294454888238
    },
    {
      "symbol": "$Boomer",
      "chain": "solana",
      "token_address": "9JDbQsoPEKeQMJLnUpvVV3kvqGvmkyPNo1T3qEhyS8GM",
      "score": 0.05,
      "fdv": 11416,
      "volume_h24": 85348.37,
      "price_change_h1": -67.61,
      "price_change_h6": -67.61,
      "avg_buy_usd": 0,
      "total_buy_usd": 0,
      "buyer_count": 0,
      "buyer_wallets": [],
      "top_buyer_score": 0,
      "gmgn_smart_wallets": 0,
      "mcap_tier": "<$50K",
      "dex_url": "https://dexscreener.com/solana/5b2tfukkirwtgkr2hypuj7fpkejdzrk7famvpymhtzfn",
      "positives": [
        "burned"
      ],
      "age_hours": 0.30158450378417967
    },
    {
      "symbol": "dutch",
      "chain": "solana",
      "token_address": "55rwXhHqZUVKTVbAusyvPYirdqqfeoPUVjx1ZR8xpump",
      "score": 0.02,
      "fdv": 7273,
      "volume_h24": 147452.66,
      "price_change_h1": -44.32,
      "price_change_h6": -79.6,
      "avg_buy_usd": 0,
      "total_buy_usd": 0,
      "buyer_count": 0,
      "buyer_wallets": [],
      "top_buyer_score": 0,
      "gmgn_smart_wallets": 0,
      "mcap_tier": "<$50K",
      "dex_url": "https://dexscreener.com/solana/ch5khhpugl6pv8pukjiolqhiapdqy23kcpa1wcmvzvax",
      "positives": [
        "burned"
      ],
      "age_hours": 1.3418623176405164
    },
    {
      "symbol": "CONDOM",
      "chain": "solana",
      "token_address": "AU2LVjjFFF53UDEE5GdTaHE41P8uaVE4AtzAXkBTSUpd",
      "score": 0.01,
      "fdv": 3752,
      "volume_h24": 89798.01,
      "price_change_h1": -49.83,
      "price_change_h6": -89.42,
      "avg_buy_usd": 0,
      "total_buy_usd": 0,
      "buyer_count": 0,
      "buyer_wallets": [],
      "top_buyer_score": 0,
      "gmgn_smart_wallets": 0,
      "mcap_tier": "<$50K",
      "dex_url": "https://dexscreener.com/solana/bq3tm18rewdzf5nzwqch5c4r6jbtkfnzdxpfrl5wyj6u",
      "positives": [
        "burned"
      ],
      "age_hours": 1.0729282113986545
    },
    {
      "symbol": "DNUT",
      "chain": "solana",
      "token_address": "DvkFVc6XhnX7N6s9vgkfRCtVZymSNLmiMxtm9oCepump",
      "score": 0.01,
      "fdv": 2730,
      "volume_h24": 79086.55,
      "price_change_h1": -92.16,
      "price_change_h6": -92.16,
      "avg_buy_usd": 0,
      "total_buy_usd": 0,
      "buyer_count": 0,
      "buyer_wallets": [],
      "top_buyer_score": 0,
      "gmgn_smart_wallets": 0,
      "mcap_tier": "<$50K",
      "dex_url": "https://dexscreener.com/solana/j3yh8uyp3bw5vhrknsln6nqbxioa4chtw4bg7tbbvcpp",
      "positives": [
        "burned"
      ],
      "age_hours": 0.9354282143825955
    },
    {
      "symbol": "Duobao",
      "chain": "solana",
      "token_address": "53RUohPnCrbRcVGjvfHHHUL4cmQX68yP8Ei6poepump",
      "score": 0,
      "fdv": 7155,
      "volume_h24": 144700.02,
      "price_change_h1": -53.03,
      "price_change_h6": -79.76,
      "avg_buy_usd": 0,
      "total_buy_usd": 0,
      "buyer_count": 0,
      "buyer_wallets": [],
      "top_buyer_score": 0,
      "gmgn_smart_wallets": 0,
      "mcap_tier": "<$50K",
      "dex_url": "https://dexscreener.com/solana/gjja5nuswagqpdhdzn3y1pwyw2wehprl8j8cjoam368u",
      "positives": [],
      "age_hours": 4.84195396870931
    },
    {
      "symbol": "Donnyland",
      "chain": "solana",
      "token_address": "6KHjB7D6mXf7N3WTuV3TWX3fYAQMuGMZNvfgxxpWQEsY",
      "score": 0,
      "fdv": 8170,
      "volume_h24": 281005.73,
      "price_change_h1": -76.82,
      "price_change_h6": -77.13,
      "avg_buy_usd": 0,
      "total_buy_usd": 0,
      "buyer_count": 0,
      "buyer_wallets": [],
      "top_buyer_score": 0,
      "gmgn_smart_wallets": 0,
      "mcap_tier": "<$50K",
      "dex_url": "https://dexscreener.com/solana/j7vkpga9a2ithnakvmbxsytxmhs4qfgsgkwpophorfd7",
      "positives": [],
      "age_hours": 2.1274610900878907
    },
    {
      "symbol": "Mogged",
      "chain": "solana",
      "token_address": "3pJqNEzhYywNHTdTbA3UBjzpDu9KxD5Jo4Y98zdcpump",
      "score": 0.0,
      "fdv": 3511,
      "volume_h24": 183615.02,
      "price_change_h1": -85.36,
      "price_change_h6": -90.08,
      "avg_buy_usd": 0,
      "total_buy_usd": 0,
      "buyer_count": 0,
      "buyer_wallets": [],
      "top_buyer_score": 0,
      "gmgn_smart_wallets": 0,
      "mcap_tier": "<$50K",
      "dex_url": "https://dexscreener.com/solana/a5a9evxrpnhgdznye488usus1bfnjyvwzq5seyvufaev",
      "positives": [
        "burned"
      ],
      "age_hours": 1.582738854912652
    },
    {
      "symbol": "unchammer",
      "chain": "solana",
      "token_address": "3BdrPDgX7YWVrL95JLqnt5dHmC1SevVSEN1uf7vcpump",
      "score": 0.0,
      "fdv": 2822,
      "volume_h24": 936467.37,
      "price_change_h1": -98.18,
      "price_change_h6": -92.21,
      "avg_buy_usd": 0,
      "total_buy_usd": 0,
      "buyer_count": 0,
      "buyer_wallets": [],
      "top_buyer_score": 0,
      "gmgn_smart_wallets": 0,
      "mcap_tier": "<$50K",
      "dex_url": "https://dexscreener.com/solana/8guc32vrlcrvdafs6atzl8ecsdhfgft6fdjhpr5l1syt",
      "positives": [
        "burned"
      ],
      "age_hours": 1.472650424194336
    },
    {
      "symbol": "STONED",
      "chain": "solana",
      "token_address": "m7dFgbUrghNCgXsgDqeh4EF4vMCx7s6wMCYhU72pump",
      "score": 0,
      "fdv": 2054,
      "volume_h24": 2685730.52,
      "price_change_h1": -98.13,
      "price_change_h6": -96.19,
      "avg_buy_usd": 0,
      "total_buy_usd": 0,
      "buyer_count": 0,
      "buyer_wallets": [],
      "top_buyer_score": 0,
      "gmgn_smart_wallets": 0,
      "mcap_tier": "<$50K",
      "dex_url": "https://dexscreener.com/solana/3lafmhpehmu95fbxt7hgwbtz713eduuzw7yj2l4gqcwc",
      "positives": [],
      "age_hours": 4.8944055386691625
    },
    {
      "symbol": "Trump420",
      "chain": "solana",
      "token_address": "HwU6aT1X4JTAeWJzbt6BuALr9GMeCKE9iPTKwpc7pump",
      "score": 0,
      "fdv": 2029,
      "volume_h24": 1533419.98,
      "price_change_h1": -29.01,
      "price_change_h6": -97.55,
      "avg_buy_usd": 0,
      "total_buy_usd": 0,
      "buyer_count": 0,
      "buyer_wallets": [],
      "top_buyer_score": 0,
      "gmgn_smart_wallets": 0,
      "mcap_tier": "<$50K",
      "dex_url": "https://dexscreener.com/solana/5cnjobbmyacao5h96xrerhtvw8qa3kuw45fd28awxdhy",
      "positives": [],
      "age_hours": 9.917973410847981
    },
    {
      "symbol": "DONNYLAND",
      "chain": "solana",
      "token_address": "TyMWVKCn3muPDmFDq51qwgU2BiYE7DfWULtmYyV5U4D",
      "score": 0.0,
      "fdv": 3043,
      "volume_h24": 443999.57,
      "price_change_h1": -63.59,
      "price_change_h6": -91.38,
      "avg_buy_usd": 0,
      "total_buy_usd": 0,
      "buyer_count": 0,
      "buyer_wallets": [],
      "top_buyer_score": 0,
      "gmgn_smart_wallets": 0,
      "mcap_tier": "<$50K",
      "dex_url": "https://dexscreener.com/solana/frwxzubarsctvkp3ohdjcdncr4zkmtidpldz6az5xewd",
      "positives": [
        "burned"
      ],
      "age_hours": 1.952127173055013
    },
    {
      "symbol": "Camel",
      "chain": "solana",
      "token_address": "4jjkdyJ8Nd9uz6D7oscGPgJ9HrLNhxUu5gGysp2Ypump",
      "score": 0,
      "fdv": 4586,
      "volume_h24": 258927.78,
      "price_change_h1": -35.71,
      "price_change_h6": -86.76,
      "avg_buy_usd": 0,
      "total_buy_usd": 0,
      "buyer_count": 0,
      "buyer_wallets": [],
      "top_buyer_score": 0,
      "gmgn_smart_wallets": 0,
      "mcap_tier": "<$50K",
      "dex_url": "https://dexscreener.com/solana/a2jiuyqcv6ois7svhhxugeqlcvsd31gpxxahhbz5rugx",
      "positives": [],
      "age_hours": 2.8969055457221136
    },
    {
      "symbol": "MGGA",
      "chain": "solana",
      "token_address": "4zZJwayrRLpMV8fiDjVa9ipvVVRQeap46SUaKpZ9pump",
      "score": 0,
      "fdv": 2063,
      "volume_h24": 643426.18,
      "price_change_h1": -25.33,
      "price_change_h6": -94.19,
      "avg_buy_usd": 0,
      "total_buy_usd": 0,
      "buyer_count": 0,
      "buyer_wallets": [],
      "top_buyer_score": 0,
      "gmgn_smart_wallets": 0,
      "mcap_tier": "<$50K",
      "dex_url": "https://dexscreener.com/solana/ajtogbktghnttykuhn7imbspkgjvqkqectflxsqyinr5",
      "positives": [],
      "age_hours": 2.3535721969265406
    },
    {
      "symbol": "HERMES",
      "chain": "solana",
      "token_address": "CUV9qfVFZhZibuMjbgRjSmF6RRXgP2UztPEYvC2upump",
      "score": 0,
      "fdv": 4709,
      "volume_h24": 154500.32,
      "price_change_h1": -8.55,
      "price_change_h6": -85.65,
      "avg_buy_usd": 0,
      "total_buy_usd": 0,
      "buyer_count": 0,
      "buyer_wallets": [],
      "top_buyer_score": 0,
      "gmgn_smart_wallets": 0,
      "mcap_tier": "<$50K",
      "dex_url": "https://dexscreener.com/solana/96qgmbavhsamjspxvivclwj3keqkdcc1mhhhfsszgjko",
      "positives": [],
      "age_hours": 4.6735722224934895
    },
    {
      "symbol": "420",
      "chain": "solana",
      "token_address": "5DuvLnKL6XhC9teLcXNXcP1Ju6gtNRX2zooWys5Qpump",
      "score": 0,
      "fdv": 2994,
      "volume_h24": 822465.06,
      "price_change_h1": 0.12,
      "price_change_h6": -93.12,
      "avg_buy_usd": 0,
      "total_buy_usd": 0,
      "buyer_count": 0,
      "buyer_wallets": [],
      "top_buyer_score": 0,
      "gmgn_smart_wallets": 0,
      "mcap_tier": "<$50K",
      "dex_url": "https://dexscreener.com/solana/dcq9f91aw19xheyfkebgd5bju7q542pmbpxffpxmdkfn",
      "positives": [],
      "age_hours": 5.978850003729926
    },
    {
      "symbol": "GUIA",
      "chain": "solana",
      "token_address": "Co5MdAPgwF1AUMmSzXxbKKLXDM23tP37t2FENESJpump",
      "score": 0,
      "fdv": 2813,
      "volume_h24": 262596.01,
      "price_change_h1": -20.24,
      "price_change_h6": -92.07,
      "avg_buy_usd": 0,
      "total_buy_usd": 0,
      "buyer_count": 0,
      "buyer_wallets": [],
      "top_buyer_score": 0,
      "gmgn_smart_wallets": 0,
      "mcap_tier": "<$50K",
      "dex_url": "https://dexscreener.com/solana/3jztwyjyrbn6wzchanphkyzgvczhyqxpdr7d1j2hp59t",
      "positives": [],
      "age_hours": 4.578849993421766
    },
    {
      "symbol": "Feow",
      "chain": "solana",
      "token_address": "44ugfGyvuH46Vpv1j58HLLfto6p9PvBh37mbnC9kpump",
      "score": 0,
      "fdv": 3045,
      "volume_h24": 51757.8,
      "price_change_h1": 4.24,
      "price_change_h6": -91.18,
      "avg_buy_usd": 0,
      "total_buy_usd": 0,
      "buyer_count": 0,
      "buyer_wallets": [],
      "top_buyer_score": 0,
      "gmgn_smart_wallets": 0,
      "mcap_tier": "<$50K",
      "dex_url": "https://dexscreener.com/solana/8aamwrww7ydiqyvkmp8q7qgyip17ekakpdh7wfsnfxbq",
      "positives": [],
      "age_hours": 5.732231750623915
    },
    {
      "symbol": "CAESAR",
      "chain": "solana",
      "token_address": "DsxQAzSgEgQ7ARgdnCEhhS98RLoqar7xAMoy7hAbpump",
      "score": 0,
      "fdv": 2101,
      "volume_h24": 1333380.33,
      "price_change_h1": -4.42,
      "price_change_h6": -97.8,
      "avg_buy_usd": 0,
      "total_buy_usd": 0,
      "buyer_count": 0,
      "buyer_wallets": [],
      "top_buyer_score": 0,
      "gmgn_smart_wallets": 0,
      "mcap_tier": "<$50K",
      "dex_url": "https://dexscreener.com/solana/8ndyaacatyec5vnedtw9qidskbqutnknidw2kmks9evn",
      "positives": [],
      "age_hours": 10.418251184624566
    },
    {
      "symbol": "hijabunc",
      "chain": "solana",
      "token_address": "APXdsrtBf8ensg45iEvc3BjWGbJvRTXsSJJCtN29pump",
      "score": 0,
      "fdv": 3198,
      "volume_h24": 4747251.67,
      "price_change_h1": -0.57,
      "price_change_h6": 5.18,
      "avg_buy_usd": 0,
      "total_buy_usd": 0,
      "buyer_count": 0,
      "buyer_wallets": [],
      "top_buyer_score": 0,
      "gmgn_smart_wallets": 0,
      "mcap_tier": "<$50K",
      "dex_url": "https://dexscreener.com/solana/gdxpccftuq4ocfkzbq1cidf8i2ke4eenzng5sb4yguuu",
      "positives": [],
      "age_hours": 24.46895372016059
    },
    {
      "symbol": "SS",
      "chain": "solana",
      "token_address": "6dpEhzqDLEKscR7VXYbyzRS8PwdR9nPKzWQhaz6tpump",
      "score": 0,
      "fdv": 1823,
      "volume_h24": 637201.06,
      "price_change_h1": null,
      "price_change_h6": -2.47,
      "avg_buy_usd": 0,
      "total_buy_usd": 0,
      "buyer_count": 0,
      "buyer_wallets": [],
      "top_buyer_score": 0,
      "gmgn_smart_wallets": 0,
      "mcap_tier": "<$50K",
      "dex_url": "https://dexscreener.com/solana/vgetjq6lxqhnce1drszbookepgqf1p84kvpjf4cduqd",
      "positives": [],
      "age_hours": 15.454872621663412
    },
    {
      "symbol": "uncel",
      "chain": "solana",
      "token_address": "87osnJqhtnrYn6RytkyE7t8zv8KYaEiBARfeiK8spump",
      "score": 0,
      "fdv": 3750,
      "volume_h24": 2267551.5,
      "price_change_h1": 18.86,
      "price_change_h6": -4.13,
      "avg_buy_usd": 0,
      "total_buy_usd": 0,
      "buyer_count": 0,
      "buyer_wallets": [],
      "top_buyer_score": 0,
      "gmgn_smart_wallets": 0,
      "mcap_tier": "<$50K",
      "dex_url": "https://dexscreener.com/solana/4yqrkdcrssn7zoqxowmqks3jzq3e6qckqfvnrdv2ceaa",
      "positives": [],
      "age_hours": 10.27792813164605
    },
    {
      "symbol": "MOONDOGE",
      "chain": "solana",
      "token_address": "BiUkiHrBS7pfBXBD9H4vYfcVxGQXdLmMqTJR9Djepump",
      "score": 0,
      "fdv": 2007,
      "volume_h24": 308846.57,
      "price_change_h1": -1.1,
      "price_change_h6": -2.16,
      "avg_buy_usd": 0,
      "total_buy_usd": 0,
      "buyer_count": 0,
      "buyer_wallets": [],
      "top_buyer_score": 0,
      "gmgn_smart_wallets": 0,
      "mcap_tier": "<$50K",
      "dex_url": "https://dexscreener.com/solana/bkr6jn7jxcuq2ymoy3jrfew16b3t1tfjrdv2qh2skeqc",
      "positives": [],
      "age_hours": 13.992094841240776
    },
    {
      "symbol": "ASTERMISA",
      "chain": "solana",
      "token_address": "E1TNoDaWqvjV67Z2DTVnSWbFFTLVsZvKxvdtxVLRpump",
      "score": 0,
      "fdv": 2006,
      "volume_h24": 1160820.91,
      "price_change_h1": -1.07,
      "price_change_h6": 4.05,
      "avg_buy_usd": 0,
      "total_buy_usd": 0,
      "buyer_count": 0,
      "buyer_wallets": [],
      "top_buyer_score": 0,
      "gmgn_smart_wallets": 0,
      "mcap_tier": "<$50K",
      "dex_url": "https://dexscreener.com/solana/dbead7srve7y7uwzncyghqujqfle9wwmkotmdqtwohhf",
      "positives": [],
      "age_hours": 13.06292817179362
    },
    {
      "symbol": "ASTROPEPE",
      "chain": "solana",
      "token_address": "ESNMKWzWzBCCoDYooJKuri1gSYWVoLTJC11hkXh2pump",
      "score": 0,
      "fdv": 5620,
      "volume_h24": 3247399.45,
      "price_change_h1": 5.09,
      "price_change_h6": -98.57,
      "avg_buy_usd": 0,
      "total_buy_usd": 0,
      "buyer_count": 0,
      "buyer_wallets": [],
      "top_buyer_score": 0,
      "gmgn_smart_wallets": 0,
      "mcap_tier": "<$50K",
      "dex_url": "https://dexscreener.com/solana/hafucubqnqqosj44echp3tyj8ybcye7hqdczfmsftszc",
      "positives": [],
      "age_hours": 9.817094834662543
    },
    {
      "symbol": "ASTROID",
      "chain": "solana",
      "token_address": "4Zf7E5kATj5nheipNqnyvX3btebd2Nrc4rBxS9Kppump",
      "score": 0,
      "fdv": 24831,
      "volume_h24": 3089320.29,
      "price_change_h1": 5.13,
      "price_change_h6": -39.93,
      "avg_buy_usd": 0,
      "total_buy_usd": 0,
      "buyer_count": 0,
      "buyer_wallets": [],
      "top_buyer_score": 0,
      "gmgn_smart_wallets": 0,
      "mcap_tier": "<$50K",
      "dex_url": "https://dexscreener.com/solana/fnzf8kksrfjbsey8fuafckptpf2oxhp3yp2tmqjmqsvz",
      "positives": [],
      "age_hours": 12.041261532253689
    },
    {
      "symbol": "GayHormuz",
      "chain": "solana",
      "token_address": "8T9nS9KDEqYCeJXFfZrz1G6L15nnQVJCUnmoSmydpump",
      "score": 0,
      "fdv": 44658,
      "volume_h24": 69013.57,
      "price_change_h1": 0.06,
      "price_change_h6": 7.47,
      "avg_buy_usd": 0,
      "total_buy_usd": 0,
      "buyer_count": 0,
      "buyer_wallets": [],
      "top_buyer_score": 0,
      "gmgn_smart_wallets": 0,
      "mcap_tier": "<$50K",
      "dex_url": "https://dexscreener.com/solana/4gcmnru6yqhp7wjqgxbvhh91ujtgme8w6hzntjki6fvz",
      "positives": [],
      "age_hours": 24.467555036417643
    },
    {
      "symbol": "INSIDER",
      "chain": "solana",
      "token_address": "39WcTaHpWyWputedmNn5QnjvMPqLXVAEVAAW4dC1pump",
      "score": 0,
      "fdv": 3727,
      "volume_h24": 116686.04,
      "price_change_h1": -9.06,
      "price_change_h6": -72.8,
      "avg_buy_usd": 0,
      "total_buy_usd": 0,
      "buyer_count": 0,
      "buyer_wallets": [],
      "top_buyer_score": 0,
      "gmgn_smart_wallets": 0,
      "mcap_tier": "<$50K",
      "dex_url": "https://dexscreener.com/solana/2fmwg13jwb8zwqw9fjyndsy7zz14tm4kx8rvugtvfyf8",
      "positives": [],
      "age_hours": 6.810287308078342
    },
    {
      "symbol": "TROG",
      "chain": "solana",
      "token_address": "7ChGWkwQ2ZXWgrXFnUQKnUjW2dgePXdnN7dPsRu6pump",
      "score": 0,
      "fdv": 3776,
      "volume_h24": 260623.63,
      "price_change_h1": -0.52,
      "price_change_h6": -62.64,
      "avg_buy_usd": 0,
      "total_buy_usd": 0,
      "buyer_count": 0,
      "buyer_wallets": [],
      "top_buyer_score": 0,
      "gmgn_smart_wallets": 0,
      "mcap_tier": "<$50K",
      "dex_url": "https://dexscreener.com/solana/9vnaffszwjqs5nwyjdkplbpn9rw1qwz6aqzx4seanyqt",
      "positives": [],
      "age_hours": 8.729731754760742
    },
    {
      "symbol": "Achi",
      "chain": "solana",
      "token_address": "AMoJLuQdW3Kxt89Kqb118LfDtSngv9rLhNUA4xadpump",
      "score": 0,
      "fdv": 3596,
      "volume_h24": 358319.48,
      "price_change_h1": -13.55,
      "price_change_h6": -78.68,
      "avg_buy_usd": 0,
      "total_buy_usd": 0,
      "buyer_count": 0,
      "buyer_wallets": [],
      "top_buyer_score": 0,
      "gmgn_smart_wallets": 0,
      "mcap_tier": "<$50K",
      "dex_url": "https://dexscreener.com/solana/5y7cuk8jzz9gcq9nkgv4sec5v3h4m5mzotwsj1pgdk6p",
      "positives": [],
      "age_hours": 10.162787312147353
    },
    {
      "symbol": "BOOGIE",
      "chain": "solana",
      "token_address": "3UrG28wYXBkhxGCfX1HGLdd2g8ahDxqntp5nUAPnpump",
      "score": 0,
      "fdv": 1908,
      "volume_h24": 578416.87,
      "price_change_h1": null,
      "price_change_h6": -22.1,
      "avg_buy_usd": 0,
      "total_buy_usd": 0,
      "buyer_count": 0,
      "buyer_wallets": [],
      "top_buyer_score": 0,
      "gmgn_smart_wallets": 0,
      "mcap_tier": "<$50K",
      "dex_url": "https://dexscreener.com/solana/9rgvfzdtcs3w3pdfv7swhgd3gbr287extvuwqzuanq4a",
      "positives": [],
      "age_hours": 17.893898426310223
    },
    {
      "symbol": "FUMES",
      "chain": "solana",
      "token_address": "7Yw5SrMfv25yhQCD3tXLY6ipgSVsJydA6Lc46MAEpump",
      "score": 0,
      "fdv": 2571,
      "volume_h24": 1321368.9,
      "price_change_h1": 5.34,
      "price_change_h6": -3.97,
      "avg_buy_usd": 0,
      "total_buy_usd": 0,
      "buyer_count": 0,
      "buyer_wallets": [],
      "top_buyer_score": 0,
      "gmgn_smart_wallets": 0,
      "mcap_tier": "<$50K",
      "dex_url": "https://dexscreener.com/solana/bexyqvwnteg1nt342ncouq63otp6shqbgsbcghuqtrfx",
      "positives": [],
      "age_hours": 9.89806509379069
    },
    {
      "symbol": "PONYROID",
      "chain": "solana",
      "token_address": "7asMYe2EFJy2yo77hVTg4WiDWMMWypGTTFpVZ6r6pump",
      "score": 0,
      "fdv": 2054,
      "volume_h24": 813089.65,
      "price_change_h1": 0.09,
      "price_change_h6": -4.88,
      "avg_buy_usd": 0,
      "total_buy_usd": 0,
      "buyer_count": 0,
      "buyer_wallets": [],
      "top_buyer_score": 0,
      "gmgn_smart_wallets": 0,
      "mcap_tier": "<$50K",
      "dex_url": "https://dexscreener.com/solana/b4cpkqezapen6v5cfgkiq5azqumertkm7qoc63cgwnsv",
      "positives": [],
      "age_hours": 10.966434405178495
    },
    {
      "symbol": "elon.exe",
      "chain": "solana",
      "token_address": "DGpejDi8tFqxgChRETXKkxoeLGUyKCEWzS9Yvvjzpump",
      "score": 0,
      "fdv": 3069,
      "volume_h24": 664616.39,
      "price_change_h1": -1.96,
      "price_change_h6": -39.08,
      "avg_buy_usd": 0,
      "total_buy_usd": 0,
      "buyer_count": 0,
      "buyer_wallets": [],
      "top_buyer_score": 0,
      "gmgn_smart_wallets": 0,
      "mcap_tier": "<$50K",
      "dex_url": "https://dexscreener.com/solana/9bxe83kducrvfqyhrgae1me9pur5dz67agxtpwv3ymjy",
      "positives": [],
      "age_hours": 12.29065144422743
    },
    {
      "symbol": "cattoo",
      "chain": "solana",
      "token_address": "DApfd2KmFxT9zQcMLTiFjtHW3Yi71JKP85hFzTFMpump",
      "score": 0,
      "fdv": 8028,
      "volume_h24": 367730.35,
      "price_change_h1": 13.86,
      "price_change_h6": -49.24,
      "avg_buy_usd": 0,
      "total_buy_usd": 0,
      "buyer_count": 0,
      "buyer_wallets": [],
      "top_buyer_score": 0,
      "gmgn_smart_wallets": 0,
      "mcap_tier": "<$50K",
      "dex_url": "https://dexscreener.com/solana/6c7kymhr8r6k6u1vsqjf3bfwkzghwnlsihceiavelttv",
      "positives": [],
      "age_hours": 12.061762559611003
    }
  ]
}