{
  "generated_at_iso": "2026-04-22T04:40:03.132153+00:00",
  "tokens": [
    {
      "symbol": "PEACE",
      "chain": "solana",
      "token_address": "HcbsqQC3sn2LMwbjVafiEd8nJ2ATZHH2wXH4xqV2pump",
      "score": 13.33,
      "fdv": 8439201,
      "volume_h24": 2315551.39,
      "price_change_h1": 26.94,
      "price_change_h6": 26.82,
      "avg_buy_usd": 0,
      "total_buy_usd": 0,
      "buyer_count": 0,
      "buyer_wallets": [],
      "top_buyer_score": 0,
      "gmgn_smart_wallets": 0,
      "mcap_tier": "$1M-$10M",
      "dex_url": "https://dexscreener.com/solana/dfzrjanvgbirpbbgihakbzr2gyqxwfgfjq3n78rzrmny",
      "positives": [
        "burned"
      ],
      "age_hours": 154.54179778971354
    },
    {
      "symbol": "Flork",
      "chain": "solana",
      "token_address": "8WFLEGsNYVEkcGfdihZBztufJVMJXJNjpmuDgijypump",
      "score": 10.12,
      "fdv": 722559,
      "volume_h24": 1645002.78,
      "price_change_h1": 60.26,
      "price_change_h6": 4859,
      "avg_buy_usd": 0,
      "total_buy_usd": 0,
      "buyer_count": 0,
      "buyer_wallets": [],
      "top_buyer_score": 0,
      "gmgn_smart_wallets": 0,
      "mcap_tier": "$250K-$1M",
      "dex_url": "https://dexscreener.com/solana/ckm7nfwsej89fgd4buykfj4exepmgrzrdxydcpmoits4",
      "positives": [
        "burned"
      ],
      "age_hours": 1693.895964452379
    },
    {
      "symbol": "MUGA",
      "chain": "solana",
      "token_address": "4VLgZ7w4K4hQX12HghZyx9GpqYFLbmZveAX5893Tpump",
      "score": 9.36,
      "fdv": 39475,
      "volume_h24": 40016.56,
      "price_change_h1": 10.17,
      "price_change_h6": 10.17,
      "avg_buy_usd": 0,
      "total_buy_usd": 0,
      "buyer_count": 0,
      "buyer_wallets": [],
      "top_buyer_score": 0,
      "gmgn_smart_wallets": 0,
      "mcap_tier": "<$50K",
      "dex_url": "https://dexscreener.com/solana/htwkf662esdmwifttlldzeynnwfjyamw7asdtac3k8ir",
      "positives": [
        "burned"
      ],
      "age_hours": 0.7919775520833333
    },
    {
      "symbol": "BILLI",
      "chain": "solana",
      "token_address": "HrGqFD7jqZ3a41YvJXeQquzXwgsCR3Jv72wPzE9Dbrrr",
      "score": 7.44,
      "fdv": 72751,
      "volume_h24": 257822.04,
      "price_change_h1": 1.4,
      "price_change_h6": 121,
      "avg_buy_usd": 0,
      "total_buy_usd": 0,
      "buyer_count": 0,
      "buyer_wallets": [],
      "top_buyer_score": 0,
      "gmgn_smart_wallets": 0,
      "mcap_tier": "$50K-$250K",
      "dex_url": "https://dexscreener.com/solana/fmjnfz5kcd8c6pqa37zhtguhnbgudfoyemecr14einzz",
      "positives": [
        "burned"
      ],
      "age_hours": 200.89402001498752
    },
    {
      "symbol": "DB",
      "chain": "solana",
      "token_address": "43SXvpf4c41t2uErsw7aL6w5qhnie6BXSSPqiTcTpump",
      "score": 6.33,
      "fdv": 30141,
      "volume_h24": 1786.33,
      "price_change_h1": 21.5,
      "price_change_h6": 21.5,
      "avg_buy_usd": 0,
      "total_buy_usd": 0,
      "buyer_count": 0,
      "buyer_wallets": [],
      "top_buyer_score": 0,
      "gmgn_smart_wallets": 0,
      "mcap_tier": "<$50K",
      "dex_url": "https://dexscreener.com/solana/4mlvkoatb8c2kotdrmktu8ryx95qzaztnrscjbrr7pje",
      "positives": [
        "burned"
      ],
      "age_hours": 8972.457810889282
    },
    {
      "symbol": "FLORK",
      "chain": "solana",
      "token_address": "Ar3QbizYS8tGysqqEmeBu66Ga5snYFnRE5JhaxjRgGS",
      "score": 6.07,
      "fdv": 111508,
      "volume_h24": 964732.66,
      "price_change_h1": 34.04,
      "price_change_h6": 4223,
      "avg_buy_usd": 0,
      "total_buy_usd": 0,
      "buyer_count": 0,
      "buyer_wallets": [],
      "top_buyer_score": 0,
      "gmgn_smart_wallets": 0,
      "mcap_tier": "$50K-$250K",
      "dex_url": "https://dexscreener.com/solana/d9xnne9dhs2ulxslnzdk7wkwzamecqro8cpsbj8pmbdq",
      "positives": [
        "burned"
      ],
      "age_hours": 1014.4141997755263
    },
    {
      "symbol": "DankDoge",
      "chain": "solana",
      "token_address": "5GhCbdx8uHT1wJ88gj3fYSLpsqEW9x4s6NXJ5GPJpump",
      "score": 5.31,
      "fdv": 35849,
      "volume_h24": 132362.49,
      "price_change_h1": 117,
      "price_change_h6": 364,
      "avg_buy_usd": 0,
      "total_buy_usd": 0,
      "buyer_count": 0,
      "buyer_wallets": [],
      "top_buyer_score": 0,
      "gmgn_smart_wallets": 0,
      "mcap_tier": "<$50K",
      "dex_url": "https://dexscreener.com/solana/5gfh6drhdbuzjgbpydvgxunwb2fngaaqhlkig5y3epvi",
      "positives": [
        "burned"
      ],
      "age_hours": 3650.2605886697725
    },
    {
      "symbol": "ETF",
      "chain": "solana",
      "token_address": "Fi7G1b2Exqcy4XB9Hpq9K6CgP9Hcr4MwhEBXM7hqpump",
      "score": 4.25,
      "fdv": 728829,
      "volume_h24": 1025796.65,
      "price_change_h1": 18.89,
      "price_change_h6": 1057,
      "avg_buy_usd": 0,
      "total_buy_usd": 0,
      "buyer_count": 0,
      "buyer_wallets": [],
      "top_buyer_score": 0,
      "gmgn_smart_wallets": 0,
      "mcap_tier": "$250K-$1M",
      "dex_url": "https://dexscreener.com/solana/7zkb88pyfxynwzgmdcd3mjgh628u784rzkc2ebkcxdny",
      "positives": [
        "burned"
      ],
      "age_hours": 3.1530886496310764
    },
    {
      "symbol": "EXPEDITION",
      "chain": "solana",
      "token_address": "mhsJciTgcQaGSv7o9Ex5HzhDXnW87g973RyC7Gvpump",
      "score": 4.05,
      "fdv": 182386,
      "volume_h24": 428916.82,
      "price_change_h1": 246,
      "price_change_h6": 375,
      "avg_buy_usd": 0,
      "total_buy_usd": 0,
      "buyer_count": 0,
      "buyer_wallets": [],
      "top_buyer_score": 0,
      "gmgn_smart_wallets": 0,
      "mcap_tier": "$50K-$250K",
      "dex_url": "https://dexscreener.com/solana/asbdnzh5ccd4prp4wff2paqrp9zg5mn6xa7byhgaoyzs",
      "positives": [
        "burned"
      ],
      "age_hours": 1.0064706991916232
    },
    {
      "symbol": "BABYASTEROID",
      "chain": "bsc",
      "token_address": "0x0bb212d0f2e29f5ab51bf293f5c57d6c5fde4444",
      "score": 3.57,
      "fdv": 366436,
      "volume_h24": 563680.56,
      "price_change_h1": 22.76,
      "price_change_h6": 20.97,
      "avg_buy_usd": 0,
      "total_buy_usd": 0,
      "buyer_count": 0,
      "buyer_wallets": [],
      "top_buyer_score": 0,
      "gmgn_smart_wallets": 0,
      "mcap_tier": "$250K-$1M",
      "dex_url": "https://dexscreener.com/bsc/0xcfb78bfdd9fcadf44be190e5cdd33e022e89a263",
      "positives": [],
      "age_hours": 72.6969665645345
    },
    {
      "symbol": "420",
      "chain": "solana",
      "token_address": "8JA6nUFHESxu7ocytAwF6e4E41NE4YCgGBtpti9pump",
      "score": 3.54,
      "fdv": 378036,
      "volume_h24": 921456.28,
      "price_change_h1": -12.38,
      "price_change_h6": 766,
      "avg_buy_usd": 0,
      "total_buy_usd": 0,
      "buyer_count": 0,
      "buyer_wallets": [],
      "top_buyer_score": 0,
      "gmgn_smart_wallets": 0,
      "mcap_tier": "$250K-$1M",
      "dex_url": "https://dexscreener.com/solana/fljndoe7ekhpcxurumg9dqyr4ynmnhooxxkg9utykjnx",
      "positives": [
        "burned"
      ],
      "age_hours": 2.8898040303548176
    },
    {
      "symbol": "SIF",
      "chain": "solana",
      "token_address": "554b7hiCBBbd1wT7XvqRMhsCcFuHSFXkfZdTeVzupump",
      "score": 2.66,
      "fdv": 18399,
      "volume_h24": 860500.66,
      "price_change_h1": -21.79,
      "price_change_h6": -6.89,
      "avg_buy_usd": 0,
      "total_buy_usd": 0,
      "buyer_count": 0,
      "buyer_wallets": [],
      "top_buyer_score": 0,
      "gmgn_smart_wallets": 0,
      "mcap_tier": "<$50K",
      "dex_url": "https://dexscreener.com/solana/8hflqa1stnk1ps9qtjfegllukeh3uyjrha5vku1q4pwg",
      "positives": [
        "burned"
      ],
      "age_hours": 19.998088658650715
    },
    {
      "symbol": "\u4f60\u6211\u501f",
      "chain": "bsc",
      "token_address": "0x88884c70a4a67813bda46e7e8aa1f300b0c87777",
      "score": 2.52,
      "fdv": 324679,
      "volume_h24": 817975.58,
      "price_change_h1": 7.38,
      "price_change_h6": 36.96,
      "avg_buy_usd": 0,
      "total_buy_usd": 0,
      "buyer_count": 0,
      "buyer_wallets": [],
      "top_buyer_score": 0,
      "gmgn_smart_wallets": 0,
      "mcap_tier": "$250K-$1M",
      "dex_url": "https://dexscreener.com/bsc/0xb81cf029dbe3a7fddeba1466b2d6755178eda0a3",
      "positives": [],
      "age_hours": 22.452522117852105
    },
    {
      "symbol": "\u706b\u661f",
      "chain": "bsc",
      "token_address": "0x1b29a493718f9f6312af99264bcc81e75c637777",
      "score": 1.98,
      "fdv": 130247,
      "volume_h24": 72490.71,
      "price_change_h1": 8.05,
      "price_change_h6": 24.19,
      "avg_buy_usd": 0,
      "total_buy_usd": 0,
      "buyer_count": 0,
      "buyer_wallets": [],
      "top_buyer_score": 0,
      "gmgn_smart_wallets": 0,
      "mcap_tier": "$50K-$250K",
      "dex_url": "https://dexscreener.com/bsc/0x0dda13e9aed0036f698f6f7a716413aa4cc6b2ad",
      "positives": [],
      "age_hours": 2304.2339110077583
    },
    {
      "symbol": "BOOMER",
      "chain": "solana",
      "token_address": "586A5dMVhMc9kgzqbRJcMRq877oWmJhaGviYvzZSpump",
      "score": 1.87,
      "fdv": 10283,
      "volume_h24": 15421.8,
      "price_change_h1": 37.49,
      "price_change_h6": 30.27,
      "avg_buy_usd": 0,
      "total_buy_usd": 0,
      "buyer_count": 0,
      "buyer_wallets": [],
      "top_buyer_score": 0,
      "gmgn_smart_wallets": 0,
      "mcap_tier": "<$50K",
      "dex_url": "https://dexscreener.com/solana/86mh3sbzuedqkzjkxrs7qdg3kt6saku46emhmftdqn8f",
      "positives": [
        "burned"
      ],
      "age_hours": 3486.7997553355576
    },
    {
      "symbol": "Maya ",
      "chain": "solana",
      "token_address": "BkHwSqqJTbeFevvdqMDmpcbMU1eQRLrvY4BBM9Wcpump",
      "score": 1.59,
      "fdv": 21845,
      "volume_h24": 51985,
      "price_change_h1": -36.34,
      "price_change_h6": -36.34,
      "avg_buy_usd": 0,
      "total_buy_usd": 0,
      "buyer_count": 0,
      "buyer_wallets": [],
      "top_buyer_score": 0,
      "gmgn_smart_wallets": 0,
      "mcap_tier": "<$50K",
      "dex_url": "https://dexscreener.com/solana/h97t7spx7t9klyrst8kjuae4jsh7adlqy9bud8gmw2r2",
      "positives": [
        "burned"
      ],
      "age_hours": 0.4705880609809028
    },
    {
      "symbol": "\u66fc\u6ce2",
      "chain": "bsc",
      "token_address": "0x21ec3092eaef51015963747d2340fc04461f4444",
      "score": 1.5,
      "fdv": 23906,
      "volume_h24": 1464.49,
      "price_change_h1": 12.95,
      "price_change_h6": 12.95,
      "avg_buy_usd": 0,
      "total_buy_usd": 0,
      "buyer_count": 0,
      "buyer_wallets": [],
      "top_buyer_score": 0,
      "gmgn_smart_wallets": 0,
      "mcap_tier": "<$50K",
      "dex_url": "https://dexscreener.com/bsc/0x0f714de4bbad3ac104c8f7448d0b38c6ffbdaf87",
      "positives": [],
      "age_hours": 4706.885577669881
    },
    {
      "symbol": "T26",
      "chain": "solana",
      "token_address": "DLsGGp9se7uUzE1SKbWD4hur1c9bjXnK3ADUejXJpump",
      "score": 1.49,
      "fdv": 51155,
      "volume_h24": 13546.76,
      "price_change_h1": -12.08,
      "price_change_h6": -0.27,
      "avg_buy_usd": 0,
      "total_buy_usd": 0,
      "buyer_count": 0,
      "buyer_wallets": [],
      "top_buyer_score": 0,
      "gmgn_smart_wallets": 0,
      "mcap_tier": "$50K-$250K",
      "dex_url": "https://dexscreener.com/solana/frt1bbpbpxwrzesmdk7wfofjhnl1m4fstlqpvfwjyppm",
      "positives": [
        "burned"
      ],
      "age_hours": 286.2773040412055
    },
    {
      "symbol": "derp",
      "chain": "solana",
      "token_address": "CCzmP9jbSV1smWNUjpEhS6qJAYzLi3tGfNJMpmEBpump",
      "score": 1.47,
      "fdv": 11449,
      "volume_h24": 2421.06,
      "price_change_h1": 23.74,
      "price_change_h6": 63,
      "avg_buy_usd": 0,
      "total_buy_usd": 0,
      "buyer_count": 0,
      "buyer_wallets": [],
      "top_buyer_score": 0,
      "gmgn_smart_wallets": 0,
      "mcap_tier": "<$50K",
      "dex_url": "https://dexscreener.com/solana/92gjtfekschmu8fp4pdkmaqwgyzw6pyw6bxgq7xgqg3y",
      "positives": [
        "burned"
      ],
      "age_hours": 1691.949526260783
    },
    {
      "symbol": "\u5171\u5efa",
      "chain": "bsc",
      "token_address": "0xb2acf3ae051c7f0b0b8de90cbb4ed99312574444",
      "score": 1.3,
      "fdv": 4154680,
      "volume_h24": 1403229.64,
      "price_change_h1": 5.26,
      "price_change_h6": 10.21,
      "avg_buy_usd": 0,
      "total_buy_usd": 0,
      "buyer_count": 0,
      "buyer_wallets": [],
      "top_buyer_score": 0,
      "gmgn_smart_wallets": 0,
      "mcap_tier": "$1M-$10M",
      "dex_url": "https://dexscreener.com/bsc/0x843170d02c676175f86f85288dde9569b5570034",
      "positives": [],
      "age_hours": 347.7247443432617
    },
    {
      "symbol": "jelly",
      "chain": "bsc",
      "token_address": "0xf581ee357f11d7478fafd183b4a41347c35a4444",
      "score": 1.18,
      "fdv": 684338,
      "volume_h24": 383433.6,
      "price_change_h1": 2.21,
      "price_change_h6": -2.49,
      "avg_buy_usd": 0,
      "total_buy_usd": 0,
      "buyer_count": 0,
      "buyer_wallets": [],
      "top_buyer_score": 0,
      "gmgn_smart_wallets": 0,
      "mcap_tier": "$250K-$1M",
      "dex_url": "https://dexscreener.com/bsc/0x3e321573b17a1a157b1254a8d5275682475cce13",
      "positives": [],
      "age_hours": 307.4802998998345
    },
    {
      "symbol": "\u5e01\u5b89\u4eba\u751f",
      "chain": "bsc",
      "token_address": "0x30e08b8a52c6d96e109ef116c2eac1ccbe9e7777",
      "score": 1.12,
      "fdv": 28630,
      "volume_h24": 49582.33,
      "price_change_h1": -18.99,
      "price_change_h6": -4.23,
      "avg_buy_usd": 0,
      "total_buy_usd": 0,
      "buyer_count": 0,
      "buyer_wallets": [],
      "top_buyer_score": 0,
      "gmgn_smart_wallets": 0,
      "mcap_tier": "<$50K",
      "dex_url": "https://dexscreener.com/bsc/0xaddf4109f225117c4d8202ccc5522161c75c32e0",
      "positives": [],
      "age_hours": 13.3916887826199
    },
    {
      "symbol": "MHGA",
      "chain": "solana",
      "token_address": "2b9iJWg3sppbAAQMuKBXa1iuSSsuPvKwcdiA4VdNpump",
      "score": 1.06,
      "fdv": 19000,
      "volume_h24": 453020.27,
      "price_change_h1": -5.35,
      "price_change_h6": -3.95,
      "avg_buy_usd": 0,
      "total_buy_usd": 0,
      "buyer_count": 0,
      "buyer_wallets": [],
      "top_buyer_score": 0,
      "gmgn_smart_wallets": 0,
      "mcap_tier": "<$50K",
      "dex_url": "https://dexscreener.com/solana/8okfo9vs25mgnjohz9hss2b5ps4oenfymdsc5unfknte",
      "positives": [
        "burned"
      ],
      "age_hours": 15.927255322062175
    },
    {
      "symbol": "Hermes",
      "chain": "solana",
      "token_address": "J5DnHXXmKsXmCAeSvPRc5qR64ruYKcZHKwZijv9HnZgK",
      "score": 1.06,
      "fdv": 37522,
      "volume_h24": 11586.44,
      "price_change_h1": -13.21,
      "price_change_h6": -4.62,
      "avg_buy_usd": 0,
      "total_buy_usd": 0,
      "buyer_count": 0,
      "buyer_wallets": [],
      "top_buyer_score": 0,
      "gmgn_smart_wallets": 0,
      "mcap_tier": "<$50K",
      "dex_url": "https://dexscreener.com/solana/erik5wup3okzduegn6jepg8rahumeq6mjqtmnkqvy8aq",
      "positives": [
        "burned"
      ],
      "age_hours": 1327.8367977885607
    },
    {
      "symbol": "wif2",
      "chain": "solana",
      "token_address": "9tCjcZFwaqMFSFkiYDRAGd3kxChxVguHDCREb6eSpump",
      "score": 0.99,
      "fdv": 86897,
      "volume_h24": 3964607.09,
      "price_change_h1": -22.5,
      "price_change_h6": -51.8,
      "avg_buy_usd": 0,
      "total_buy_usd": 0,
      "buyer_count": 0,
      "buyer_wallets": [],
      "top_buyer_score": 0,
      "gmgn_smart_wallets": 0,
      "mcap_tier": "$50K-$250K",
      "dex_url": "https://dexscreener.com/solana/89kpf7x5sqdm8ko4gvzzslzd7w57tg9jutcqokqxcimi",
      "positives": [
        "burned"
      ],
      "age_hours": 22.922532508409287
    },
    {
      "symbol": "\u5916\u661f\u5c0f\u7eff\u732b",
      "chain": "bsc",
      "token_address": "0xe117c0d405778f7416ebb3a2c389f215f44a4444",
      "score": 0.84,
      "fdv": 62640,
      "volume_h24": 35850.38,
      "price_change_h1": 10.21,
      "price_change_h6": -0.87,
      "avg_buy_usd": 0,
      "total_buy_usd": 0,
      "buyer_count": 0,
      "buyer_wallets": [],
      "top_buyer_score": 0,
      "gmgn_smart_wallets": 0,
      "mcap_tier": "$50K-$250K",
      "dex_url": "https://dexscreener.com/bsc/0xc9a00ecccf274cea88453db2a0517300b0b07faa",
      "positives": [],
      "age_hours": 811.6997443334961
    },
    {
      "symbol": "OFFCHAIN",
      "chain": "solana",
      "token_address": "BPiECaSntw8LVGYimofpNcU5eKrjrSvKz5VY7mr9pump",
      "score": 0.81,
      "fdv": 180814,
      "volume_h24": 337764.59,
      "price_change_h1": -22.19,
      "price_change_h6": 89.75,
      "avg_buy_usd": 0,
      "total_buy_usd": 0,
      "buyer_count": 0,
      "buyer_wallets": [],
      "top_buyer_score": 0,
      "gmgn_smart_wallets": 0,
      "mcap_tier": "$50K-$250K",
      "dex_url": "https://dexscreener.com/solana/dgwpzxjizizngyyecytkmwvxqir213rzmuux7nhewtr",
      "positives": [
        "burned"
      ],
      "age_hours": 11.14013112854004
    },
    {
      "symbol": "FLORK",
      "chain": "solana",
      "token_address": "4rcKcLSfXd6wg2CRxwC45gpCJk9gms4kJuCpjK6zo1Qd",
      "score": 0.77,
      "fdv": 10629,
      "volume_h24": 213499.06,
      "price_change_h1": -0.57,
      "price_change_h6": 1063,
      "avg_buy_usd": 0,
      "total_buy_usd": 0,
      "buyer_count": 0,
      "buyer_wallets": [],
      "top_buyer_score": 0,
      "gmgn_smart_wallets": 0,
      "mcap_tier": "<$50K",
      "dex_url": "https://dexscreener.com/solana/2uumglyat1w9cee3zocpcwuqgntgnhcptjn5mw8uckl2",
      "positives": [],
      "age_hours": 20363.906470706108
    },
    {
      "symbol": "GARGOYLE",
      "chain": "solana",
      "token_address": "2dMWhpuK6ux9Z5Tz8vEXjLA3xx71415UqByC6tvCpump",
      "score": 0.75,
      "fdv": 66035,
      "volume_h24": 426396.78,
      "price_change_h1": -40.77,
      "price_change_h6": 84.6,
      "avg_buy_usd": 0,
      "total_buy_usd": 0,
      "buyer_count": 0,
      "buyer_wallets": [],
      "top_buyer_score": 0,
      "gmgn_smart_wallets": 0,
      "mcap_tier": "$50K-$250K",
      "dex_url": "https://dexscreener.com/solana/gnq5ofzi7kocx5karfzh1fitobhfkayhvf1kijrddch4",
      "positives": [
        "burned"
      ],
      "age_hours": 4.514575573933919
    },
    {
      "symbol": "Aliens",
      "chain": "bsc",
      "token_address": "0x3bc4162e09d943b390c54281ad78e277aaf74444",
      "score": 0.75,
      "fdv": 178199,
      "volume_h24": 95272.16,
      "price_change_h1": -5.8,
      "price_change_h6": -5.19,
      "avg_buy_usd": 0,
      "total_buy_usd": 0,
      "buyer_count": 0,
      "buyer_wallets": [],
      "top_buyer_score": 0,
      "gmgn_smart_wallets": 0,
      "mcap_tier": "$50K-$250K",
      "dex_url": "https://dexscreener.com/bsc/0x5bbf5a073844efa30f256b7d9ecf8fd61a7d224e",
      "positives": [],
      "age_hours": 1466.9247443391248
    },
    {
      "symbol": "CLAWB",
      "chain": "solana",
      "token_address": "A2bt3Mwrn9fxGFLTA3UT7dt8WMcR7tABKih4fyuiMTWn",
      "score": 0.49,
      "fdv": 21242,
      "volume_h24": 140691.73,
      "price_change_h1": -55.08,
      "price_change_h6": -42.72,
      "avg_buy_usd": 0,
      "total_buy_usd": 0,
      "buyer_count": 0,
      "buyer_wallets": [],
      "top_buyer_score": 0,
      "gmgn_smart_wallets": 0,
      "mcap_tier": "<$50K",
      "dex_url": "https://dexscreener.com/solana/5ffvry5hu9etacadmwncv7jmmq3hdaabibyvjrcrgqha",
      "positives": [
        "burned"
      ],
      "age_hours": 0.9981866796875
    },
    {
      "symbol": "TRENCHR",
      "chain": "solana",
      "token_address": "6FFm8pGhAdWQNRLHNpFvYzx7tTMrhKvU6NzPwALhpump",
      "score": 0.02,
      "fdv": 16314,
      "volume_h24": 90932.43,
      "price_change_h1": -62.76,
      "price_change_h6": -54.46,
      "avg_buy_usd": 0,
      "total_buy_usd": 0,
      "buyer_count": 0,
      "buyer_wallets": [],
      "top_buyer_score": 0,
      "gmgn_smart_wallets": 0,
      "mcap_tier": "<$50K",
      "dex_url": "https://dexscreener.com/solana/gy32sbe453hnwyhfda9kmhxrbmzn88uhgamv3l99eemq",
      "positives": [
        "burned"
      ],
      "age_hours": 1.3362422361924913
    },
    {
      "symbol": "SOUL",
      "chain": "solana",
      "token_address": "H9GYmDuw3oepuaV5CqDjS4JT5fBHGwz9ezGu7n71pump",
      "score": 0.01,
      "fdv": 3012,
      "volume_h24": 18252.73,
      "price_change_h1": -91.6,
      "price_change_h6": -91.6,
      "avg_buy_usd": 0,
      "total_buy_usd": 0,
      "buyer_count": 0,
      "buyer_wallets": [],
      "top_buyer_score": 0,
      "gmgn_smart_wallets": 0,
      "mcap_tier": "<$50K",
      "dex_url": "https://dexscreener.com/solana/ciuq7ehehnhwrxuhkjb4mzw93mwm1d13chmf6luo2myf",
      "positives": [
        "burned"
      ],
      "age_hours": 0.5736929203965929
    },
    {
      "symbol": "Curak",
      "chain": "solana",
      "token_address": "EEmHzKKTcuG4XS178MuYjbp4DPF7s3xZcsGoJfCpump",
      "score": 0,
      "fdv": 7313,
      "volume_h24": 358032.1,
      "price_change_h1": -3.32,
      "price_change_h6": -5.93,
      "avg_buy_usd": 0,
      "total_buy_usd": 0,
      "buyer_count": 0,
      "buyer_wallets": [],
      "top_buyer_score": 0,
      "gmgn_smart_wallets": 0,
      "mcap_tier": "<$50K",
      "dex_url": "https://dexscreener.com/solana/jdb4wsxbkdtcskrkeh7nbsmorhtxkbccthdqfa48nlb1",
      "positives": [],
      "age_hours": 13.286699765489367
    },
    {
      "symbol": "ASTROPEPE",
      "chain": "solana",
      "token_address": "ESNMKWzWzBCCoDYooJKuri1gSYWVoLTJC11hkXh2pump",
      "score": 0,
      "fdv": 4621,
      "volume_h24": 3251864.88,
      "price_change_h1": -3.95,
      "price_change_h6": -8.26,
      "avg_buy_usd": 0,
      "total_buy_usd": 0,
      "buyer_count": 0,
      "buyer_wallets": [],
      "top_buyer_score": 0,
      "gmgn_smart_wallets": 0,
      "mcap_tier": "<$50K",
      "dex_url": "https://dexscreener.com/solana/hafucubqnqqosj44echp3tyj8ybcye7hqdczfmsftszc",
      "positives": [],
      "age_hours": 22.333088656277127
    },
    {
      "symbol": "uncel",
      "chain": "solana",
      "token_address": "87osnJqhtnrYn6RytkyE7t8zv8KYaEiBARfeiK8spump",
      "score": 0,
      "fdv": 2579,
      "volume_h24": 2268660.09,
      "price_change_h1": -0.55,
      "price_change_h6": -7.61,
      "avg_buy_usd": 0,
      "total_buy_usd": 0,
      "buyer_count": 0,
      "buyer_wallets": [],
      "top_buyer_score": 0,
      "gmgn_smart_wallets": 0,
      "mcap_tier": "<$50K",
      "dex_url": "https://dexscreener.com/solana/4yqrkdcrssn7zoqxowmqks3jzq3e6qckqfvnrdv2ceaa",
      "positives": [],
      "age_hours": 22.79392199557834
    },
    {
      "symbol": "Real",
      "chain": "solana",
      "token_address": "GqQeLdAZtRPy2QhJb9CqVSfp1MUuUdx9doo74WMVpump",
      "score": 0,
      "fdv": 7212,
      "volume_h24": 66540.96,
      "price_change_h1": 35.04,
      "price_change_h6": -78.33,
      "avg_buy_usd": 0,
      "total_buy_usd": 0,
      "buyer_count": 0,
      "buyer_wallets": [],
      "top_buyer_score": 0,
      "gmgn_smart_wallets": 0,
      "mcap_tier": "<$50K",
      "dex_url": "https://dexscreener.com/solana/hdx6dhrctpdhkb188nc1sxghmpnrqxssgtfmqpark6by",
      "positives": [],
      "age_hours": 2.7634151403130427
    },
    {
      "symbol": "Roadster",
      "chain": "solana",
      "token_address": "6wmubHn7vnEcqcngsVK31stSVgUJq7cTTzYiqN2Mpump",
      "score": 0,
      "fdv": 2256,
      "volume_h24": 1169092.79,
      "price_change_h1": 6.55,
      "price_change_h6": -97.83,
      "avg_buy_usd": 0,
      "total_buy_usd": 0,
      "buyer_count": 0,
      "buyer_wallets": [],
      "top_buyer_score": 0,
      "gmgn_smart_wallets": 0,
      "mcap_tier": "<$50K",
      "dex_url": "https://dexscreener.com/solana/au9rzhqdrsclfwq2su9hcuywnknfm8r5xockfs1ryamt",
      "positives": [],
      "age_hours": 8.369804034423828
    },
    {
      "symbol": "ALIEN",
      "chain": "solana",
      "token_address": "J5L5TtPbbzbd9MiE57kQNjpxK55n8e2hEGs3a2W5pump",
      "score": 0,
      "fdv": 2268,
      "volume_h24": 406634.88,
      "price_change_h1": -0.22,
      "price_change_h6": 3.87,
      "avg_buy_usd": 0,
      "total_buy_usd": 0,
      "buyer_count": 0,
      "buyer_wallets": [],
      "top_buyer_score": 0,
      "gmgn_smart_wallets": 0,
      "mcap_tier": "<$50K",
      "dex_url": "https://dexscreener.com/solana/htfvumj449sow1cq5z7um9fsiff9xmrg7kdxv9tcyhgb",
      "positives": [],
      "age_hours": 8.806470701972113
    },
    {
      "symbol": "Trump420",
      "chain": "solana",
      "token_address": "HwU6aT1X4JTAeWJzbt6BuALr9GMeCKE9iPTKwpc7pump",
      "score": 0,
      "fdv": 2173,
      "volume_h24": 1533678.81,
      "price_change_h1": -0.28,
      "price_change_h6": 2.18,
      "avg_buy_usd": 0,
      "total_buy_usd": 0,
      "buyer_count": 0,
      "buyer_wallets": [],
      "top_buyer_score": 0,
      "gmgn_smart_wallets": 0,
      "mcap_tier": "<$50K",
      "dex_url": "https://dexscreener.com/solana/5cnjobbmyacao5h96xrerhtvw8qa3kuw45fd28awxdhy",
      "positives": [],
      "age_hours": 22.43397070373535
    },
    {
      "symbol": "CAM",
      "chain": "solana",
      "token_address": "6FpJiqQ7FcogK2aby6xVDSuiPhEwVY7wQr7rE38Apump",
      "score": 0,
      "fdv": 37250,
      "volume_h24": 2097708.01,
      "price_change_h1": -2.94,
      "price_change_h6": -46.12,
      "avg_buy_usd": 0,
      "total_buy_usd": 0,
      "buyer_count": 0,
      "buyer_wallets": [],
      "top_buyer_score": 0,
      "gmgn_smart_wallets": 0,
      "mcap_tier": "<$50K",
      "dex_url": "https://dexscreener.com/solana/fwp4xdsu9mctumhmjtbnnlmwgnaz2qo6aezdv8ujh6p6",
      "positives": [],
      "age_hours": 9.172075571424696
    }
  ]
}