{
  "wallets": [
    {
      "address": "RaVenxw8kykBbW7KGBaBsb7fDkkBYK4uJVDSFun6ZxR",
      "chain": "solana",
      "wallet_score": 28.0,
      "total_profit": 99.44090704403055,
      "win_rate": 1.0,
      "avg_roi": 0.028776234095894783,
      "total_trades": 124,
      "wallet_tags": "TOP40,sandwich_bot",
      "avg_hold_hours": null,
      "sm_tokens_held": 4,
      "sm_tokens": [
        "QBIO",
        "BIO",
        "GLDx",
        "WSOL"
      ]
    },
    {
      "address": "3oe7aYLUw2Pkbm7QMAhAjn5WbzaoG9tigkrX1mAecr1P",
      "chain": "solana",
      "wallet_score": 24.0,
      "total_profit": 214.84546805546495,
      "win_rate": 1.0,
      "avg_roi": 0.02099137099869825,
      "total_trades": 33,
      "wallet_tags": "TOP99,smart_degen",
      "avg_hold_hours": null,
      "sm_tokens_held": 1,
      "sm_tokens": [
        "Lobstar"
      ]
    },
    {
      "address": "hnu5iBK8UoHb51UFsH1RYTUAYdrhjHvV5YMTf9T1CYN",
      "chain": "solana",
      "wallet_score": 12.0,
      "total_profit": 3007.942910902185,
      "win_rate": 1.0,
      "avg_roi": 0.07266523083890708,
      "total_trades": 82,
      "wallet_tags": "smart_degen,TOP14",
      "avg_hold_hours": null,
      "sm_tokens_held": 2,
      "sm_tokens": [
        "S&P500",
        "pigeon"
      ]
    },
    {
      "address": "132G9sFk454Y39oePxuyqJNAT1Vy25hWwqNk5RQKk53H",
      "chain": "solana",
      "wallet_score": 18.0,
      "total_profit": 325.50569725429,
      "win_rate": 1.0,
      "avg_roi": 0.8098317904948504,
      "total_trades": 10,
      "wallet_tags": "padre,TOP99",
      "avg_hold_hours": null,
      "sm_tokens_held": 1,
      "sm_tokens": [
        "Meme"
      ]
    },
    {
      "address": "9bh68CX7yQ4bKBZdYqkWxS5WPzAMCyA7bJaFFddwbMZd",
      "chain": "solana",
      "wallet_score": 16.0,
      "total_profit": 2.7252422627475363,
      "win_rate": 1.0,
      "avg_roi": 0.025194982952286758,
      "total_trades": 3,
      "wallet_tags": "TOP86",
      "avg_hold_hours": null,
      "sm_tokens_held": 1,
      "sm_tokens": [
        "Dinosaur"
      ]
    },
    {
      "address": "2nHsHJpkXmHb43BqSjnQFMbUcU2kWEqFqoXsbe2zv2Wi",
      "chain": "solana",
      "wallet_score": 1.0,
      "total_profit": 45.15231843308,
      "win_rate": 1.0,
      "avg_roi": 0.033859061258077604,
      "total_trades": 20,
      "wallet_tags": "TOP100,smart_degen,padre,axiom",
      "avg_hold_hours": null,
      "sm_tokens_held": 1,
      "sm_tokens": [
        "\u53d1\u8d22"
      ]
    },
    {
      "address": "6nBi2HFVZHJF6Kn2zvr1ninZkjZNrc1XiQhGzXjg4GF",
      "chain": "solana",
      "wallet_score": 0,
      "total_profit": 94.8544809886063,
      "win_rate": 0.5,
      "avg_roi": 0.13266127549576423,
      "total_trades": 27,
      "wallet_tags": "TOP75,TOP76",
      "avg_hold_hours": null,
      "sm_tokens_held": 2,
      "sm_tokens": [
        "NORMIE",
        "WSOL"
      ]
    },
    {
      "address": "7BVsMqCRoeEtvVeasYGrRhy83gHr5ZSJBnpV7QeCFQs4",
      "chain": "solana",
      "wallet_score": 0,
      "total_profit": 311.57449834505,
      "win_rate": 1.0,
      "avg_roi": 0.3697620410960566,
      "total_trades": 7,
      "wallet_tags": "TOP49,axiom",
      "avg_hold_hours": null,
      "sm_tokens_held": 2,
      "sm_tokens": [
        "ascend",
        "luck"
      ]
    },
    {
      "address": "HV56TXHsEzNd1bpia84zGkrhvSVuBayG5vh9KjneoYMf",
      "chain": "solana",
      "wallet_score": 0,
      "total_profit": 84.52926442127,
      "win_rate": 1.0,
      "avg_roi": 0.1169081830835305,
      "total_trades": 10,
      "wallet_tags": "smart_degen,bullx,TOP99",
      "avg_hold_hours": null,
      "sm_tokens_held": 2,
      "sm_tokens": [
        "dreams",
        "pigeon"
      ]
    },
    {
      "address": "BCagckXeMChUKrHEd6fKFA1uiWDtcmCXMsqaheLiUPJd",
      "chain": "solana",
      "wallet_score": 0,
      "total_profit": -147.32231845500002,
      "win_rate": 0.0,
      "avg_roi": 0.0,
      "total_trades": 0,
      "wallet_tags": "bullx,gmgn,wash_trader,TOP21,axiom",
      "avg_hold_hours": null,
      "sm_tokens_held": 1,
      "sm_tokens": [
        "ascend"
      ]
    },
    {
      "address": "EqS3FuQ1EQs4V5tfmAKw4JmBDwvVJRyJu3x9vCy1vvtA",
      "chain": "solana",
      "wallet_score": 0,
      "total_profit": -13.16151615249,
      "win_rate": 0.0,
      "avg_roi": 0.0,
      "total_trades": 18,
      "wallet_tags": "smart_degen,TOP74",
      "avg_hold_hours": null,
      "sm_tokens_held": 1,
      "sm_tokens": [
        "luck"
      ]
    },
    {
      "address": "FTaSBuVj6w2S7XUa8fw19xrLy57DDr6kZDL6sxDXtvTP",
      "chain": "solana",
      "wallet_score": 0,
      "total_profit": -3.69924149393,
      "win_rate": 0.0,
      "avg_roi": 0.0,
      "total_trades": 8,
      "wallet_tags": "gmgn,smart_degen,TOP17",
      "avg_hold_hours": null,
      "sm_tokens_held": 1,
      "sm_tokens": [
        "dreams"
      ]
    },
    {
      "address": "0x6c7cfa1b11c420fc829ea1357700c0a1e91e2433",
      "chain": "BNB",
      "wallet_score": 0,
      "total_profit": 0,
      "win_rate": 0,
      "avg_roi": 0,
      "total_trades": 0,
      "wallet_tags": "",
      "avg_hold_hours": 0,
      "sm_tokens_held": 7,
      "sm_tokens": [
        "OK\u4eba\u751f",
        "\u5929\u624d",
        "\u81ea\u7531",
        "\u626d\u7f8a\u6b4c",
        "BNTI",
        "BNBELIEF",
        "BELIEF"
      ]
    },
    {
      "address": "0xacbd7d0a8cc98342f431a8451de73ef4d3fd7774",
      "chain": "BNB",
      "wallet_score": 0,
      "total_profit": 0,
      "win_rate": 0,
      "avg_roi": 0,
      "total_trades": 0,
      "wallet_tags": "",
      "avg_hold_hours": 0,
      "sm_tokens_held": 6,
      "sm_tokens": [
        "AI\u4e4b\u773c",
        "\u4e2d\u56fd\u9f99",
        "PIZZA",
        "FREEDOMBANK",
        "  \u8774\u8776K\u7ebf",
        "\u5c4e"
      ]
    },
    {
      "address": "FrZHQpVnDWppBn5BGVMZJ3Ub5txnnoymEsiBae6ZAZRb",
      "chain": "solana",
      "wallet_score": 0,
      "total_profit": 0,
      "win_rate": 0,
      "avg_roi": 0,
      "total_trades": 0,
      "wallet_tags": "",
      "avg_hold_hours": 0,
      "sm_tokens_held": 6,
      "sm_tokens": [
        "worth",
        "Peepa",
        "income",
        "BabyBull",
        "bio/acc",
        "DUMBMONEY"
      ]
    },
    {
      "address": "0xae22a2f01e181c5e34decf95d67a39d0d52335e0",
      "chain": "base",
      "wallet_score": 0,
      "total_profit": 0,
      "win_rate": 0,
      "avg_roi": 0,
      "total_trades": 0,
      "wallet_tags": "",
      "avg_hold_hours": 0,
      "sm_tokens_held": 5,
      "sm_tokens": [
        "CLIPBRAIN",
        "PILLED",
        "VUETAIO",
        "flETH",
        "VEIN"
      ]
    },
    {
      "address": "0x36ffd46d96927d8aa5ff53b4aba9ce79eb218641",
      "chain": "BNB",
      "wallet_score": 0,
      "total_profit": 0,
      "win_rate": 0,
      "avg_roi": 0,
      "total_trades": 0,
      "wallet_tags": "",
      "avg_hold_hours": 0,
      "sm_tokens_held": 4,
      "sm_tokens": [
        "\u8774\u8776PEPE",
        "AI\u4e4b\u773c",
        "dmt-nat",
        "\u6708\u5883\u63a2\u7d22"
      ]
    },
    {
      "address": "0xae9b2082c9ef1edc7dba94e7297a1ec00da6cbd1",
      "chain": "base",
      "wallet_score": 0,
      "total_profit": 0,
      "win_rate": 0,
      "avg_roi": 0,
      "total_trades": 0,
      "wallet_tags": "",
      "avg_hold_hours": 0,
      "sm_tokens_held": 4,
      "sm_tokens": [
        "FD",
        "OREWARS",
        "flETH",
        "Marty"
      ]
    },
    {
      "address": "0x711281c1b26aaed86e40e4caaf76c1962b45e161",
      "chain": "base",
      "wallet_score": 0,
      "total_profit": 0,
      "win_rate": 0,
      "avg_roi": 0,
      "total_trades": 0,
      "wallet_tags": "",
      "avg_hold_hours": 0,
      "sm_tokens_held": 3,
      "sm_tokens": [
        "ClawBank",
        "cyb3rwr3n",
        "GITLAWB"
      ]
    },
    {
      "address": "0x84b9d311099df7bd6340441cd821015a0dacadeb",
      "chain": "BNB",
      "wallet_score": 0,
      "total_profit": 0,
      "win_rate": 0,
      "avg_roi": 0,
      "total_trades": 0,
      "wallet_tags": "",
      "avg_hold_hours": 0,
      "sm_tokens_held": 3,
      "sm_tokens": [
        "ATM\u534f\u8bae",
        "\u5723\u7532\u866b",
        "WINVAULT"
      ]
    },
    {
      "address": "DtVW93ZP44qLvxgNbyDUcHhJFEYUxLD8qEEb5bXJKeWx",
      "chain": "solana",
      "wallet_score": 0,
      "total_profit": 0,
      "win_rate": 0,
      "avg_roi": 0,
      "total_trades": 0,
      "wallet_tags": "",
      "avg_hold_hours": 0,
      "sm_tokens_held": 3,
      "sm_tokens": [
        "BULL",
        "ELON",
        "WSOL"
      ]
    },
    {
      "address": "0x0432744f8ded18d6f434a23d3c93a5551b2525df",
      "chain": "BNB",
      "wallet_score": 0,
      "total_profit": 0,
      "win_rate": 0,
      "avg_roi": 0,
      "total_trades": 0,
      "wallet_tags": "",
      "avg_hold_hours": 0,
      "sm_tokens_held": 2,
      "sm_tokens": [
        "BYSON",
        "ATM\u534f\u8bae"
      ]
    },
    {
      "address": "0x2f84ebb2f7f8edcf8e83a75a12f32bd8d99de3e0",
      "chain": "base",
      "wallet_score": 0,
      "total_profit": 0,
      "win_rate": 0,
      "avg_roi": 0,
      "total_trades": 0,
      "wallet_tags": "",
      "avg_hold_hours": 0,
      "sm_tokens_held": 2,
      "sm_tokens": [
        "HermesOS",
        "FAT"
      ]
    },
    {
      "address": "0x68e195687c041cba055c948d6b7cda2311537367",
      "chain": "base",
      "wallet_score": 0,
      "total_profit": 0,
      "win_rate": 0,
      "avg_roi": 0,
      "total_trades": 0,
      "wallet_tags": "",
      "avg_hold_hours": 0,
      "sm_tokens_held": 2,
      "sm_tokens": [
        "SUPERGEMMA",
        "COLONY"
      ]
    },
    {
      "address": "0x7668236f5333d8ac6e4e9f662208966ba5d6b4ed",
      "chain": "BNB",
      "wallet_score": 0,
      "total_profit": 0,
      "win_rate": 0,
      "avg_roi": 0,
      "total_trades": 0,
      "wallet_tags": "",
      "avg_hold_hours": 0,
      "sm_tokens_held": 2,
      "sm_tokens": [
        "\u5e01\u5708\u8036\u7a23"
      ]
    },
    {
      "address": "0x9c0d8cd805b018589457cee045fd714359c29514",
      "chain": "BNB",
      "wallet_score": 0,
      "total_profit": 0,
      "win_rate": 0,
      "avg_roi": 0,
      "total_trades": 0,
      "wallet_tags": "",
      "avg_hold_hours": 0,
      "sm_tokens_held": 2,
      "sm_tokens": [
        "PEPE",
        "\u5e01\u5b89\u65f6\u4ee3"
      ]
    },
    {
      "address": "0xe88b895873883431b1ac49ede8e8194be8967e0b",
      "chain": "BNB",
      "wallet_score": 0,
      "total_profit": 0,
      "win_rate": 0,
      "avg_roi": 0,
      "total_trades": 0,
      "wallet_tags": "",
      "avg_hold_hours": 0,
      "sm_tokens_held": 2,
      "sm_tokens": [
        "  \u8774\u8776K\u7ebf",
        "WINVAULT"
      ]
    },
    {
      "address": "BkC8T3b8y67ALXkbjK9sqwzyWaqa8b3nWkfhkiKsLoaY",
      "chain": "solana",
      "wallet_score": 0,
      "total_profit": 0,
      "win_rate": 0,
      "avg_roi": 0,
      "total_trades": 0,
      "wallet_tags": "",
      "avg_hold_hours": 0,
      "sm_tokens_held": 2,
      "sm_tokens": [
        "FOMO",
        "CRAFT"
      ]
    },
    {
      "address": "G9QgVrF6onFT7L3qC2Yu74awhxiTqf3fRpc8QAirN79X",
      "chain": "solana",
      "wallet_score": 0,
      "total_profit": 0,
      "win_rate": 0,
      "avg_roi": 0,
      "total_trades": 0,
      "wallet_tags": "",
      "avg_hold_hours": 0,
      "sm_tokens_held": 2,
      "sm_tokens": [
        "\u53d1\u8d22",
        "WSOL"
      ]
    },
    {
      "address": "XJ7tbEKnrwvioTxABhEtwmG4AWkGEDDJASstUzBgh7x",
      "chain": "solana",
      "wallet_score": 0,
      "total_profit": 0,
      "win_rate": 0,
      "avg_roi": 0,
      "total_trades": 0,
      "wallet_tags": "",
      "avg_hold_hours": 0,
      "sm_tokens_held": 2,
      "sm_tokens": [
        "\u53d1\u8d22",
        "WSOL"
      ]
    },
    {
      "address": "0x0ea9a897391ea905ae19a9d54183c7cdb45b60f4",
      "chain": "BNB",
      "wallet_score": 0,
      "total_profit": 0,
      "win_rate": 0,
      "avg_roi": 0,
      "total_trades": 0,
      "wallet_tags": "",
      "avg_hold_hours": 0,
      "sm_tokens_held": 1,
      "sm_tokens": [
        "BNBELIEF"
      ]
    },
    {
      "address": "0x1b6a12836b59741fc6e0eac37800a6131e95d498",
      "chain": "BNB",
      "wallet_score": 0,
      "total_profit": 0,
      "win_rate": 0,
      "avg_roi": 0,
      "total_trades": 0,
      "wallet_tags": "",
      "avg_hold_hours": 0,
      "sm_tokens_held": 1,
      "sm_tokens": [
        "\u56de\u58f0\u6c60"
      ]
    },
    {
      "address": "0x2072e13174b8861313776e455b2140d648e2af46",
      "chain": "BNB",
      "wallet_score": 0,
      "total_profit": 0,
      "win_rate": 0,
      "avg_roi": 0,
      "total_trades": 0,
      "wallet_tags": "",
      "avg_hold_hours": 0,
      "sm_tokens_held": 1,
      "sm_tokens": [
        "Babe.fun"
      ]
    },
    {
      "address": "0x67411c465c0761efbcb48f6947cdeddaabab9da5",
      "chain": "BNB",
      "wallet_score": 0,
      "total_profit": 0,
      "win_rate": 0,
      "avg_roi": 0,
      "total_trades": 0,
      "wallet_tags": "",
      "avg_hold_hours": 0,
      "sm_tokens_held": 1,
      "sm_tokens": [
        "X Chat"
      ]
    },
    {
      "address": "0x740cfe0bb5d83539a487f76b09f997ab5606d554",
      "chain": "BNB",
      "wallet_score": 0,
      "total_profit": 0,
      "win_rate": 0,
      "avg_roi": 0,
      "total_trades": 0,
      "wallet_tags": "",
      "avg_hold_hours": 0,
      "sm_tokens_held": 1,
      "sm_tokens": [
        "\u6cb9\u7ba1\u732b"
      ]
    },
    {
      "address": "0x97158d350703e2a40d617aa09b13182744d05606",
      "chain": "BNB",
      "wallet_score": 0,
      "total_profit": 0,
      "win_rate": 0,
      "avg_roi": 0,
      "total_trades": 0,
      "wallet_tags": "",
      "avg_hold_hours": 0,
      "sm_tokens_held": 1,
      "sm_tokens": [
        "FRDI"
      ]
    },
    {
      "address": "0x9a2a1daca07556faca114b8e8485d4b1d9ab873a",
      "chain": "BNB",
      "wallet_score": 0,
      "total_profit": 0,
      "win_rate": 0,
      "avg_roi": 0,
      "total_trades": 0,
      "wallet_tags": "",
      "avg_hold_hours": 0,
      "sm_tokens_held": 1,
      "sm_tokens": [
        "\u5929\u624d"
      ]
    },
    {
      "address": "0x9ca9be4a5f2f191295b366f26c6bddcdca12845f",
      "chain": "BNB",
      "wallet_score": 0,
      "total_profit": 0,
      "win_rate": 0,
      "avg_roi": 0,
      "total_trades": 0,
      "wallet_tags": "",
      "avg_hold_hours": 0,
      "sm_tokens_held": 1,
      "sm_tokens": [
        "\u5ff5\u5ff5"
      ]
    },
    {
      "address": "0xb74c5797e301522bc86c3ced29ada4b3aa6b08a9",
      "chain": "BNB",
      "wallet_score": 0,
      "total_profit": 0,
      "win_rate": 0,
      "avg_roi": 0,
      "total_trades": 0,
      "wallet_tags": "",
      "avg_hold_hours": 0,
      "sm_tokens_held": 1,
      "sm_tokens": [
        "\u5e01\u5708\u8036\u7a23"
      ]
    },
    {
      "address": "0xc5e9006940bff2c2396517828da52deb59b7d6a3",
      "chain": "BNB",
      "wallet_score": 0,
      "total_profit": 0,
      "win_rate": 0,
      "avg_roi": 0,
      "total_trades": 0,
      "wallet_tags": "",
      "avg_hold_hours": 0,
      "sm_tokens_held": 1,
      "sm_tokens": [
        "\u5e01\u5b89\u6545\u4e8b"
      ]
    },
    {
      "address": "0xcb03e8bb853290e5e7ac4c7bd23f878e492bf153",
      "chain": "BNB",
      "wallet_score": 0,
      "total_profit": 0,
      "win_rate": 0,
      "avg_roi": 0,
      "total_trades": 0,
      "wallet_tags": "",
      "avg_hold_hours": 0,
      "sm_tokens_held": 1,
      "sm_tokens": [
        "FRDI"
      ]
    },
    {
      "address": "0xd67adadc5eb552b2621414cf913a8743f313ce0b",
      "chain": "BNB",
      "wallet_score": 0,
      "total_profit": 0,
      "win_rate": 0,
      "avg_roi": 0,
      "total_trades": 0,
      "wallet_tags": "",
      "avg_hold_hours": 0,
      "sm_tokens_held": 1,
      "sm_tokens": [
        "BAPEKING"
      ]
    },
    {
      "address": "0xe612d98b683c0e6f87bc1311e3ed523085184b65",
      "chain": "BNB",
      "wallet_score": 0,
      "total_profit": 0,
      "win_rate": 0,
      "avg_roi": 0,
      "total_trades": 0,
      "wallet_tags": "",
      "avg_hold_hours": 0,
      "sm_tokens_held": 1,
      "sm_tokens": [
        "\u5947\u8ff9"
      ]
    },
    {
      "address": "0xf308540120584b99d6f185b25c8516cb05d64c31",
      "chain": "BNB",
      "wallet_score": 0,
      "total_profit": 0,
      "win_rate": 0,
      "avg_roi": 0,
      "total_trades": 0,
      "wallet_tags": "",
      "avg_hold_hours": 0,
      "sm_tokens_held": 1,
      "sm_tokens": [
        "\u62c9\u54ea"
      ]
    },
    {
      "address": "2dEpwaujMteZsFYCX3hwaavYKkU7kRwAwJe9XGuWNRGA",
      "chain": "solana",
      "wallet_score": 0,
      "total_profit": 0,
      "win_rate": 0,
      "avg_roi": 0,
      "total_trades": 0,
      "wallet_tags": "",
      "avg_hold_hours": 0,
      "sm_tokens_held": 1,
      "sm_tokens": [
        "Optimistic"
      ]
    },
    {
      "address": "49oSw6xmVHBXEj46B4zMLWoL7HeVtVWahRHd8pLqRtaP",
      "chain": "solana",
      "wallet_score": 0,
      "total_profit": 0,
      "win_rate": 0,
      "avg_roi": 0,
      "total_trades": 0,
      "wallet_tags": "",
      "avg_hold_hours": 0,
      "sm_tokens_held": 1,
      "sm_tokens": [
        "Fatou"
      ]
    },
    {
      "address": "5GGqDQVr2LasfmWFXSH54V6ryVrXGwkZSjkK6xR473XJ",
      "chain": "solana",
      "wallet_score": 0,
      "total_profit": 0,
      "win_rate": 0,
      "avg_roi": 0,
      "total_trades": 0,
      "wallet_tags": "",
      "avg_hold_hours": 0,
      "sm_tokens_held": 1,
      "sm_tokens": [
        "MIM"
      ]
    },
    {
      "address": "92MZw35nSRYbyVFZEu8XwB7U2Ta2mUxzN1FvDLYHEVmc",
      "chain": "solana",
      "wallet_score": 0,
      "total_profit": 401.66394246857,
      "win_rate": 1.0,
      "avg_roi": 0.03251116161200497,
      "total_trades": 85,
      "wallet_tags": "TOP63,smart_degen",
      "avg_hold_hours": null,
      "sm_tokens_held": 1,
      "sm_tokens": [
        "Hyrax"
      ]
    },
    {
      "address": "AA4CroVKXUi7fro5gJ7SYD3TR8G1DwVri4LE97rVZvJi",
      "chain": "solana",
      "wallet_score": 0,
      "total_profit": 0,
      "win_rate": 0,
      "avg_roi": 0,
      "total_trades": 0,
      "wallet_tags": "",
      "avg_hold_hours": 0,
      "sm_tokens_held": 1,
      "sm_tokens": [
        "ascend"
      ]
    },
    {
      "address": "AEqPi4RCD7uRXmMB5ec6V4ehT74Ra2kEdmqVqtHUmyLh",
      "chain": "solana",
      "wallet_score": 0,
      "total_profit": 0,
      "win_rate": 0,
      "avg_roi": 0,
      "total_trades": 0,
      "wallet_tags": "",
      "avg_hold_hours": 0,
      "sm_tokens_held": 1,
      "sm_tokens": [
        "MIM"
      ]
    },
    {
      "address": "BUjNTwwiwX6r5pcJqy27BQNstLo93Vu7HZNkoeApct6q",
      "chain": "solana",
      "wallet_score": 0,
      "total_profit": 235.13926492128,
      "win_rate": 1.0,
      "avg_roi": 1.1773349605348682,
      "total_trades": 3,
      "wallet_tags": "fresh_wallet,photon,smart_degen,TOP32",
      "avg_hold_hours": null,
      "sm_tokens_held": 1,
      "sm_tokens": [
        "MMXXVI"
      ]
    },
    {
      "address": "CVxUKFrWDYkE3gsZP9gyVmLD6XkXykk2ukKhAfNrJev8",
      "chain": "solana",
      "wallet_score": 0,
      "total_profit": 0,
      "win_rate": 0,
      "avg_roi": 0,
      "total_trades": 0,
      "wallet_tags": "",
      "avg_hold_hours": 0,
      "sm_tokens_held": 1,
      "sm_tokens": [
        "Optimistic"
      ]
    },
    {
      "address": "CqF3gUDojKuVdd6zBk2GZBTG84aAQ2b7tYeeyS18Sd2Z",
      "chain": "solana",
      "wallet_score": 0,
      "total_profit": 1236.843531048407,
      "win_rate": 1.0,
      "avg_roi": 0.09853930678085418,
      "total_trades": 41,
      "wallet_tags": "TOP61,smart_degen",
      "avg_hold_hours": null,
      "sm_tokens_held": 1,
      "sm_tokens": [
        "S&P500"
      ]
    },
    {
      "address": "DH2karT59SbVQzQKjtNomMLpdPJgvkp5NX9b2VcUvhBP",
      "chain": "solana",
      "wallet_score": 0,
      "total_profit": 0,
      "win_rate": 0,
      "avg_roi": 0,
      "total_trades": 0,
      "wallet_tags": "",
      "avg_hold_hours": 0,
      "sm_tokens_held": 1,
      "sm_tokens": [
        "moar"
      ]
    },
    {
      "address": "E2tVJXu8GFjxxYeFftLSoqz9L15qVoqpDEiFGB7YJC8s",
      "chain": "solana",
      "wallet_score": 0,
      "total_profit": 0,
      "win_rate": 0,
      "avg_roi": 0,
      "total_trades": 0,
      "wallet_tags": "",
      "avg_hold_hours": 0,
      "sm_tokens_held": 1,
      "sm_tokens": [
        "moar"
      ]
    },
    {
      "address": "GoonY5hPo63xAPCwkyWuFmQ57HWq8wj5Bevj2D222U4u",
      "chain": "solana",
      "wallet_score": 0,
      "total_profit": 0,
      "win_rate": 0,
      "avg_roi": 0,
      "total_trades": 0,
      "wallet_tags": "",
      "avg_hold_hours": 0,
      "sm_tokens_held": 1,
      "sm_tokens": [
        "fatchoi"
      ]
    },
    {
      "address": "HCQP5QBZxZRoA16jaZaC8kzMBRWhBaQa3YjYPFtFxLDd",
      "chain": "solana",
      "wallet_score": 0,
      "total_profit": 0,
      "win_rate": 0,
      "avg_roi": 0,
      "total_trades": 0,
      "wallet_tags": "",
      "avg_hold_hours": 0,
      "sm_tokens_held": 1,
      "sm_tokens": [
        "pigeon"
      ]
    },
    {
      "address": "Ha3jPXVWz2VoESCEEH8YP8StcYF7p2A2hadUEd6bqu4w",
      "chain": "solana",
      "wallet_score": 0,
      "total_profit": 0,
      "win_rate": 0,
      "avg_roi": 0,
      "total_trades": 0,
      "wallet_tags": "",
      "avg_hold_hours": 0,
      "sm_tokens_held": 1,
      "sm_tokens": [
        "pigeon"
      ]
    },
    {
      "address": "gecko1QDvtNHwqY5SjXLzuDmGDUnzu7ZEmtGHRFLr9v",
      "chain": "solana",
      "wallet_score": 0,
      "total_profit": 0,
      "win_rate": 0,
      "avg_roi": 0,
      "total_trades": 0,
      "wallet_tags": "",
      "avg_hold_hours": 0,
      "sm_tokens_held": 1,
      "sm_tokens": [
        "luck"
      ]
    }
  ],
  "generated_at_iso": "2026-04-17T04:01:25.704240+00:00"
}